<?xml version = "1.0"?>
<!DOCTYPE Component [
<!ELEMENT Component (CICB*)>
<!ATTLIST Component
Id CDATA #REQUIRED
Name CDATA #REQUIRED
Num_CICBs CDATA #REQUIRED>
<!ELEMENT CICB (Provide|Require|Block_Point|EMPTY)>
<!ATTLIST CICB
Id CDATA #REQUIRED
Name CDATA #REQUIRED>
<!ELEMENT Provide (Call_invoke_IDs|Variable_access_IDs|EMPTY)>
<!ATTLIST Provide
Num_call_invokes CDATA #REQUIRED
Num_Variable_accesses CDATA #REQUIRED>
<!ELEMENT Require (Call_invoke_IDs|Variable_access_IDs|EMPTY)>
<!ATTLIST Provide
Num_call_invokes CDATA #REQUIRED
Num_Variable_accesses CDATA #REQUIRED>
<!ELEMENT Call_invoke_IDs EMPTY>
<!ELEMENT Variable_access_IDs EMPTY>
<!ELEMENT Point_Block (Selective|Conditional|Cyclic|Data)*>
<!ATTLIST Provide
Num_points CDATA #REQUIRED
Braced CDATA #REQUIRED
Code_Loc CDATA #REQUIRED>
<!ELEMENT Selective (Point_Block*|EMPTY)>
<!ATTLIST Selective
If_Blocks CDATA #REQUIRED
Code_Loc CDATA #REQUIRED>
<!ELEMENT Conditional (Point_Block|EMPTY)>
<!ATTLIST Conditional
Code_Loc CDATA #REQUIRED>
<!ELEMENT Cyclic (Point_Block|EMPTY)>
<!ATTLIST Cyclic
Id CDATA #REQUIRED
Code_Loc CDATA #REQUIRED>
<!ELEMENT Data (Call|Variable|EMPTY)*>
<!ATTLIST Data
Data_owner CDATA #REQUIRED
Code_Loc CDATA #REQUIRED>
<!ELEMENT Call (Data|EMPTY)>
<!ATTLIST Call
Id CDATA #REQUIRED
Name CDATA #REQUIRED
Collect CDATA #REQUIRED
Access_block CDATA #REQUIRED
Home_block CDATA #REQUIRED>
<!ELEMENT Variable EMPTY>
<!ATTLIST Variable
Id CDATA #REQUIRED
Name CDATA #REQUIRED
Access CDATA #REQUIRED
Access_block CDATA #REQUIRED
Home_block CDATA #REQUIRED>
]>
<Component
Id="573"
Name="interfaces.ecpg.compatlib.informix.c"
Num_CICBs="44">
<CICB
Id="0"
Name="Master">
<Provide
Num_call_invokes="0"
Num_Variable_accesses="17">
<Call_invoke_IDs>
</Call_invoke_IDs>
<Variable_access_IDs>
112826
112827
112828
112829
112830
112831
112832
112833
112834
112835
112836
112837
112838
112839
112840
112841
112842
</Variable_access_IDs>
</Provide>
<Require
Num_call_invokes="0"
Num_Variable_accesses="1">
<Call_invoke_IDs>
</Call_invoke_IDs>
<Variable_access_IDs>
112826
</Variable_access_IDs>
</Require>
<Point_Block
Num_points="1"
Braced="Yes"
Code_Loc="(19,1),(1047,1)">
<Data
Data_owner="VariableDeclaration"
Code_Loc="(983,1),(988,17)">
<Variable
Id="112826"
Name="ivlist"
Access="Write"
Access_block="(573,0)"
Home_block="(573,0)"/>
</Data>
</Point_Block>
</CICB>
<CICB
Id="1"
Name="deccall2">
<Provide
Num_call_invokes="1"
Num_Variable_accesses="7">
<Call_invoke_IDs>
14446 
</Call_invoke_IDs>
<Variable_access_IDs>
112843
112844
112845
112846
112847
112848
112849
</Variable_access_IDs>
</Provide>
<Require
Num_call_invokes="0"
Num_Variable_accesses="7">
<Call_invoke_IDs>
</Call_invoke_IDs>
<Variable_access_IDs>
112843
112844
112845
112846
112847
112848
112849
</Variable_access_IDs>
</Require>
<Point_Block
Num_points="7"
Braced="Yes"
Code_Loc="(22,2),(54,12)">
<Conditional
Code_Loc="(26,2),(27,37)">
</Conditional>
<Conditional
Code_Loc="(29,2),(33,2)">
<Point_Block
Num_points="0"
Braced="Yes"
Code_Loc="(31,3),(32,37)">
</Point_Block>
</Conditional>
<Conditional
Code_Loc="(35,2),(40,2)">
<Point_Block
Num_points="1"
Braced="Yes"
Code_Loc="(37,3),(39,37)">
<Data
Data_owner="Expression"
Code_Loc="(38,3),(38,26)">
<Variable
Id="112843"
Name="a2"
Access="Write"
Access_block="(573,1)"
Home_block="(573,1)"/>
</Data>
</Point_Block>
</Conditional>
<Conditional
Code_Loc="(42,2),(47,2)">
<Point_Block
Num_points="1"
Braced="Yes"
Code_Loc="(44,3),(46,37)">
<Data
Data_owner="Expression"
Code_Loc="(45,3),(45,26)">
<Variable
Id="112844"
Name="a2"
Access="Write"
Access_block="(573,1)"
Home_block="(573,1)"/>
</Data>
</Point_Block>
</Conditional>
<Data
Data_owner="Expression"
Code_Loc="(49,2),(49,21)">
<Variable
Id="112845"
Name="i"
Access="Write"
Access_block="(573,1)"
Home_block="(573,1)"/>
<Variable
Id="112846"
Name="ptr"
Access="Read"
Access_block="(573,1)"
Home_block="(573,1)"/>
<Variable
Id="112847"
Name="a2"
Access="Read"
Access_block="(573,1)"
Home_block="(573,1)"/>
</Data>
<Data
Data_owner="Expression"
Code_Loc="(52,2),(52,25)">
<Variable
Id="112848"
Name="a2"
Access="Write"
Access_block="(573,1)"
Home_block="(573,1)"/>
</Data>
<Data
Data_owner="Jump"
Code_Loc="(54,2),(54,12)">
<Variable
Id="112849"
Name="i"
Access="Read"
Access_block="(573,1)"
Home_block="(573,1)"/>
</Data>
</Point_Block>
</CICB>
<CICB
Id="2"
Name="deccall3">
<Provide
Num_call_invokes="4"
Num_Variable_accesses="15">
<Call_invoke_IDs>
14447 
14448 
14449 
14450 
</Call_invoke_IDs>
<Variable_access_IDs>
112850
112851
112852
112853
112854
112855
112856
112857
112858
112859
112860
112861
112862
112863
112864
</Variable_access_IDs>
</Provide>
<Require
Num_call_invokes="0"
Num_Variable_accesses="15">
<Call_invoke_IDs>
</Call_invoke_IDs>
<Variable_access_IDs>
112850
112851
112852
112853
112854
112855
112856
112857
112858
112859
112860
112861
112862
112863
112864
</Variable_access_IDs>
</Require>
<Point_Block
Num_points="11"
Braced="Yes"
Code_Loc="(60,2),(118,12)">
<Conditional
Code_Loc="(69,2),(70,11)">
</Conditional>
<Conditional
Code_Loc="(72,2),(73,37)">
</Conditional>
<Conditional
Code_Loc="(75,2),(79,2)">
<Point_Block
Num_points="0"
Braced="Yes"
Code_Loc="(77,3),(78,37)">
</Point_Block>
</Conditional>
<Conditional
Code_Loc="(81,2),(86,2)">
<Point_Block
Num_points="1"
Braced="Yes"
Code_Loc="(83,3),(85,37)">
<Data
Data_owner="Expression"
Code_Loc="(84,3),(84,26)">
<Variable
Id="112850"
Name="a2"
Access="Write"
Access_block="(573,2)"
Home_block="(573,2)"/>
</Data>
</Point_Block>
</Conditional>
<Conditional
Code_Loc="(88,2),(94,2)">
<Point_Block
Num_points="2"
Braced="Yes"
Code_Loc="(90,3),(93,37)">
<Data
Data_owner="Expression"
Code_Loc="(91,3),(91,26)">
<Variable
Id="112851"
Name="a2"
Access="Write"
Access_block="(573,2)"
Home_block="(573,2)"/>
</Data>
<Data
Data_owner="Expression"
Code_Loc="(92,3),(92,28)">
<Variable
Id="112852"
Name="nres"
Access="Write"
Access_block="(573,2)"
Home_block="(573,2)"/>
</Data>
</Point_Block>
</Conditional>
<Conditional
Code_Loc="(96,2),(102,2)">
<Point_Block
Num_points="2"
Braced="Yes"
Code_Loc="(98,3),(101,37)">
<Data
Data_owner="Expression"
Code_Loc="(99,3),(99,26)">
<Variable
Id="112853"
Name="a2"
Access="Write"
Access_block="(573,2)"
Home_block="(573,2)"/>
</Data>
<Data
Data_owner="Expression"
Code_Loc="(100,3),(100,28)">
<Variable
Id="112854"
Name="nres"
Access="Write"
Access_block="(573,2)"
Home_block="(573,2)"/>
</Data>
</Point_Block>
</Conditional>
<Data
Data_owner="Expression"
Code_Loc="(104,2),(104,27)">
<Variable
Id="112855"
Name="i"
Access="Write"
Access_block="(573,2)"
Home_block="(573,2)"/>
<Variable
Id="112856"
Name="ptr"
Access="Read"
Access_block="(573,2)"
Home_block="(573,2)"/>
<Variable
Id="112857"
Name="a2"
Access="Read"
Access_block="(573,2)"
Home_block="(573,2)"/>
<Variable
Id="112858"
Name="nres"
Access="Read"
Access_block="(573,2)"
Home_block="(573,2)"/>
</Data>
<Conditional
Code_Loc="(106,2),(112,2)">
<Point_Block
Num_points="2"
Braced="Yes"
Code_Loc="(110,3),(111,42)">
<Data
Data_owner="Expression"
Code_Loc="(110,3),(110,42)">
<Variable
Id="112859"
Name="result"
Access="Write"
Access_block="(573,2)"
Home_block="(573,2)"/>
</Data>
<Data
Data_owner="Expression"
Code_Loc="(111,3),(111,42)">
<Variable
Id="112860"
Name="nres"
Access="Write"
Access_block="(573,2)"
Home_block="(573,2)"/>
<Variable
Id="112861"
Name="result"
Access="Read"
Access_block="(573,2)"
Home_block="(573,2)"/>
</Data>
</Point_Block>
</Conditional>
<Data
Data_owner="Expression"
Code_Loc="(114,2),(114,27)">
<Variable
Id="112862"
Name="nres"
Access="Write"
Access_block="(573,2)"
Home_block="(573,2)"/>
</Data>
<Data
Data_owner="Expression"
Code_Loc="(116,2),(116,25)">
<Variable
Id="112863"
Name="a2"
Access="Write"
Access_block="(573,2)"
Home_block="(573,2)"/>
</Data>
<Data
Data_owner="Jump"
Code_Loc="(118,2),(118,12)">
<Variable
Id="112864"
Name="i"
Access="Read"
Access_block="(573,2)"
Home_block="(573,2)"/>
</Data>
</Point_Block>
</CICB>
<CICB
Id="3"
Name="decadd">
<Provide
Num_call_invokes="0"
Num_Variable_accesses="3">
<Call_invoke_IDs>
</Call_invoke_IDs>
<Variable_access_IDs>
112865
112866
112867
</Variable_access_IDs>
</Provide>
<Require
Num_call_invokes="1"
Num_Variable_accesses="3">
<Call_invoke_IDs>
14447 
</Call_invoke_IDs>
<Variable_access_IDs>
112865
112866
112867
</Variable_access_IDs>
</Require>
<Point_Block
Num_points="2"
Braced="Yes"
Code_Loc="(125,2),(135,11)">
<Data
Data_owner="Expression"
Code_Loc="(126,2),(126,47)">
<Call
Id="14447"
Name="deccall3"
Collect="Emanated"
Access_block="(573,3)"
Home_block="(573,2)">
<Data
Data_owner="CallParamaters"
Code_Loc="(126,2),(126,47)">
<Variable
Id="112865"
Name="arg1"
Access="Read"
Access_block="(573,3)"
Home_block="(573,3)"/>
<Variable
Id="112866"
Name="arg2"
Access="Read"
Access_block="(573,3)"
Home_block="(573,3)"/>
<Variable
Id="112867"
Name="sum"
Access="Read"
Access_block="(573,3)"
Home_block="(573,3)"/>
</Data>
</Call>
</Data>
<Selective
If_Blocks="Yes"
Code_Loc="(128,2),(135,11)">
</Selective>
</Point_Block>
</CICB>
<CICB
Id="4"
Name="deccmp">
<Provide
Num_call_invokes="0"
Num_Variable_accesses="2">
<Call_invoke_IDs>
</Call_invoke_IDs>
<Variable_access_IDs>
112868
112869
</Variable_access_IDs>
</Provide>
<Require
Num_call_invokes="1"
Num_Variable_accesses="2">
<Call_invoke_IDs>
14446 
</Call_invoke_IDs>
<Variable_access_IDs>
112868
112869
</Variable_access_IDs>
</Require>
<Point_Block
Num_points="1"
Braced="Yes"
Code_Loc="(141,2),(141,51)">
<Data
Data_owner="Jump"
Code_Loc="(141,2),(141,51)">
<Call
Id="14446"
Name="deccall2"
Collect="Emanated"
Access_block="(573,4)"
Home_block="(573,1)">
<Data
Data_owner="CallParamaters"
Code_Loc="(141,2),(141,51)">
<Variable
Id="112868"
Name="arg1"
Access="Read"
Access_block="(573,4)"
Home_block="(573,4)"/>
<Variable
Id="112869"
Name="arg2"
Access="Read"
Access_block="(573,4)"
Home_block="(573,4)"/>
</Data>
</Call>
</Data>
</Point_Block>
</CICB>
<CICB
Id="5"
Name="deccopy">
<Provide
Num_call_invokes="0"
Num_Variable_accesses="2">
<Call_invoke_IDs>
</Call_invoke_IDs>
<Variable_access_IDs>
112870
112871
</Variable_access_IDs>
</Provide>
<Require
Num_call_invokes="0"
Num_Variable_accesses="2">
<Call_invoke_IDs>
</Call_invoke_IDs>
<Variable_access_IDs>
112870
112871
</Variable_access_IDs>
</Require>
<Point_Block
Num_points="1"
Braced="Yes"
Code_Loc="(147,2),(147,38)">
<Data
Data_owner="Expression"
Code_Loc="(147,2),(147,38)">
<Variable
Id="112870"
Name="target"
Access="Write"
Access_block="(573,5)"
Home_block="(573,5)"/>
<Variable
Id="112871"
Name="src"
Access="Read"
Access_block="(573,5)"
Home_block="(573,5)"/>
</Data>
</Point_Block>
</CICB>
<CICB
Id="6"
Name="ecpg_strndup">
<Provide
Num_call_invokes="1"
Num_Variable_accesses="15">
<Call_invoke_IDs>
14451 
</Call_invoke_IDs>
<Variable_access_IDs>
112872
112873
112874
112875
112876
112877
112878
112879
112880
112881
112882
112883
112884
112885
112886
</Variable_access_IDs>
</Provide>
<Require
Num_call_invokes="0"
Num_Variable_accesses="15">
<Call_invoke_IDs>
</Call_invoke_IDs>
<Variable_access_IDs>
112872
112873
112874
112875
112876
112877
112878
112879
112880
112881
112882
112883
112884
112885
112886
</Variable_access_IDs>
</Require>
<Point_Block
Num_points="5"
Braced="Yes"
Code_Loc="(153,2),(166,12)">
<Data
Data_owner="VariableDeclaration"
Code_Loc="(153,2),(153,30)">
<Variable
Id="112872"
Name="real_len"
Access="Write"
Access_block="(573,6)"
Home_block="(573,6)"/>
<Variable
Id="112873"
Name="str"
Access="Read"
Access_block="(573,6)"
Home_block="(573,6)"/>
</Data>
<Data
Data_owner="VariableDeclaration"
Code_Loc="(154,2),(154,57)">
<Variable
Id="112874"
Name="use_len"
Access="Write"
Access_block="(573,6)"
Home_block="(573,6)"/>
<Variable
Id="112875"
Name="real_len"
Access="Read"
Access_block="(573,6)"
Home_block="(573,6)"/>
<Variable
Id="112876"
Name="len"
Access="Read"
Access_block="(573,6)"
Home_block="(573,6)"/>
<Variable
Id="112877"
Name="len"
Access="Read"
Access_block="(573,6)"
Home_block="(573,6)"/>
<Variable
Id="112878"
Name="real_len"
Access="Read"
Access_block="(573,6)"
Home_block="(573,6)"/>
</Data>
<Data
Data_owner="VariableDeclaration"
Code_Loc="(156,2),(156,36)">
<Variable
Id="112879"
Name="new"
Access="Write"
Access_block="(573,6)"
Home_block="(573,6)"/>
<Variable
Id="112880"
Name="use_len"
Access="Read"
Access_block="(573,6)"
Home_block="(573,6)"/>
</Data>
<Selective
If_Blocks="Yes"
Code_Loc="(158,2),(164,17)">
<Point_Block
Num_points="2"
Braced="Yes"
Code_Loc="(160,3),(161,22)">
<Data
Data_owner="Expression"
Code_Loc="(160,3),(160,28)">
<Variable
Id="112881"
Name="new"
Access="Write"
Access_block="(573,6)"
Home_block="(573,6)"/>
<Variable
Id="112882"
Name="str"
Access="Read"
Access_block="(573,6)"
Home_block="(573,6)"/>
<Variable
Id="112883"
Name="use_len"
Access="Read"
Access_block="(573,6)"
Home_block="(573,6)"/>
</Data>
<Data
Data_owner="Expression"
Code_Loc="(161,3),(161,22)">
<Variable
Id="112884"
Name="new"
Access="Write"
Access_block="(573,6)"
Home_block="(573,6)"/>
<Variable
Id="112885"
Name="use_len"
Access="Read"
Access_block="(573,6)"
Home_block="(573,6)"/>
</Data>
</Point_Block>
</Selective>
<Data
Data_owner="Jump"
Code_Loc="(166,2),(166,12)">
<Variable
Id="112886"
Name="new"
Access="Read"
Access_block="(573,6)"
Home_block="(573,6)"/>
</Data>
</Point_Block>
</CICB>
<CICB
Id="7"
Name="deccvasc">
<Provide
Num_call_invokes="0"
Num_Variable_accesses="15">
<Call_invoke_IDs>
</Call_invoke_IDs>
<Variable_access_IDs>
112887
112888
112889
112890
112891
112892
112893
112894
112895
112896
112897
112898
112899
112900
112901
</Variable_access_IDs>
</Provide>
<Require
Num_call_invokes="1"
Num_Variable_accesses="15">
<Call_invoke_IDs>
14451 
</Call_invoke_IDs>
<Variable_access_IDs>
112887
112888
112889
112890
112891
112892
112893
112894
112895
112896
112897
112898
112899
112900
112901
</Variable_access_IDs>
</Require>
<Point_Block
Num_points="7"
Braced="Yes"
Code_Loc="(172,2),(214,12)">
<Data
Data_owner="VariableDeclaration"
Code_Loc="(173,2),(173,15)">
<Variable
Id="112887"
Name="ret"
Access="Write"
Access_block="(573,7)"
Home_block="(573,7)"/>
</Data>
<Data
Data_owner="Expression"
Code_Loc="(176,2),(176,37)">
<Variable
Id="112888"
Name="np"
Access="Write"
Access_block="(573,7)"
Home_block="(573,7)"/>
</Data>
<Conditional
Code_Loc="(177,2),(178,11)">
</Conditional>
<Data
Data_owner="Expression"
Code_Loc="(180,2),(180,29)">
<Variable
Id="112889"
Name="str"
Access="Write"
Access_block="(573,7)"
Home_block="(573,7)"/>
<Call
Id="14451"
Name="ecpg_strndup"
Collect="Emanated"
Access_block="(573,7)"
Home_block="(573,6)">
<Data
Data_owner="CallParamaters"
Code_Loc="(180,2),(180,29)">
<Variable
Id="112890"
Name="cp"
Access="Read"
Access_block="(573,7)"
Home_block="(573,7)"/>
</Data>
</Call>
</Data>
<Selective
If_Blocks="Yes"
Code_Loc="(182,2),(211,2)">
<Point_Block
Num_points="2"
Braced="Yes"
Code_Loc="(186,3),(210,3)">
<Data
Data_owner="Expression"
Code_Loc="(187,3),(187,46)">
<Variable
Id="112891"
Name="result"
Access="Write"
Access_block="(573,7)"
Home_block="(573,7)"/>
<Variable
Id="112892"
Name="str"
Access="Read"
Access_block="(573,7)"
Home_block="(573,7)"/>
</Data>
<Selective
If_Blocks="Yes"
Code_Loc="(188,3),(210,3)">
<Point_Block
Num_points="1"
Braced="Yes"
Code_Loc="(190,4),(201,4)">
<Selective
If_Blocks="No"
Code_Loc="(190,4),(201,4)">
<Point_Block
Num_points="1"
Braced="Yes"
Code_Loc="(193,6),(194,11)">
<Data
Data_owner="Expression"
Code_Loc="(193,6),(193,38)">
<Variable
Id="112893"
Name="ret"
Access="Write"
Access_block="(573,7)"
Home_block="(573,7)"/>
</Data>
</Point_Block>
<Point_Block
Num_points="1"
Braced="Yes"
Code_Loc="(196,6),(197,11)">
<Data
Data_owner="Expression"
Code_Loc="(196,6),(196,37)">
<Variable
Id="112894"
Name="ret"
Access="Write"
Access_block="(573,7)"
Home_block="(573,7)"/>
</Data>
</Point_Block>
<Point_Block
Num_points="1"
Braced="Yes"
Code_Loc="(199,6),(200,11)">
<Data
Data_owner="Expression"
Code_Loc="(199,6),(199,38)">
<Variable
Id="112895"
Name="ret"
Access="Write"
Access_block="(573,7)"
Home_block="(573,7)"/>
</Data>
</Point_Block>
</Selective>
</Point_Block>
<Point_Block
Num_points="3"
Braced="Yes"
Code_Loc="(205,4),(209,37)">
<Data
Data_owner="VariableDeclaration"
Code_Loc="(205,4),(205,51)">
<Variable
Id="112896"
Name="i"
Access="Write"
Access_block="(573,7)"
Home_block="(573,7)"/>
<Variable
Id="112897"
Name="result"
Access="Read"
Access_block="(573,7)"
Home_block="(573,7)"/>
<Variable
Id="112898"
Name="np"
Access="Read"
Access_block="(573,7)"
Home_block="(573,7)"/>
</Data>
<Data
Data_owner="Expression"
Code_Loc="(207,4),(207,16)">
<Variable
Id="112899"
Name="result"
Access="Write"
Access_block="(573,7)"
Home_block="(573,7)"/>
</Data>
<Conditional
Code_Loc="(208,4),(209,37)">
</Conditional>
</Point_Block>
</Selective>
</Point_Block>
</Selective>
<Data
Data_owner="Expression"
Code_Loc="(213,2),(213,11)">
<Variable
Id="112900"
Name="str"
Access="Write"
Access_block="(573,7)"
Home_block="(573,7)"/>
</Data>
<Data
Data_owner="Jump"
Code_Loc="(214,2),(214,12)">
<Variable
Id="112901"
Name="ret"
Access="Read"
Access_block="(573,7)"
Home_block="(573,7)"/>
</Data>
</Point_Block>
</CICB>
<CICB
Id="8"
Name="deccvdbl">
<Provide
Num_call_invokes="0"
Num_Variable_accesses="8">
<Call_invoke_IDs>
</Call_invoke_IDs>
<Variable_access_IDs>
112902
112903
112904
112905
112906
112907
112908
112909
</Variable_access_IDs>
</Provide>
<Require
Num_call_invokes="0"
Num_Variable_accesses="8">
<Call_invoke_IDs>
</Call_invoke_IDs>
<Variable_access_IDs>
112902
112903
112904
112905
112906
112907
112908
112909
</Variable_access_IDs>
</Require>
<Point_Block
Num_points="9"
Braced="Yes"
Code_Loc="(220,2),(236,17)">
<Data
Data_owner="VariableDeclaration"
Code_Loc="(221,2),(221,18)">
<Variable
Id="112902"
Name="result"
Access="Write"
Access_block="(573,8)"
Home_block="(573,8)"/>
</Data>
<Data
Data_owner="Expression"
Code_Loc="(223,2),(223,37)">
<Variable
Id="112903"
Name="np"
Access="Write"
Access_block="(573,8)"
Home_block="(573,8)"/>
</Data>
<Conditional
Code_Loc="(224,2),(225,11)">
</Conditional>
<Data
Data_owner="Expression"
Code_Loc="(227,2),(227,29)">
<Variable
Id="112904"
Name="nres"
Access="Write"
Access_block="(573,8)"
Home_block="(573,8)"/>
</Data>
<Conditional
Code_Loc="(228,2),(229,37)">
</Conditional>
<Data
Data_owner="Expression"
Code_Loc="(231,2),(231,48)">
<Variable
Id="112905"
Name="result"
Access="Write"
Access_block="(573,8)"
Home_block="(573,8)"/>
<Variable
Id="112906"
Name="dbl"
Access="Read"
Access_block="(573,8)"
Home_block="(573,8)"/>
<Variable
Id="112907"
Name="nres"
Access="Read"
Access_block="(573,8)"
Home_block="(573,8)"/>
</Data>
<Conditional
Code_Loc="(232,2),(233,47)">
</Conditional>
<Data
Data_owner="Expression"
Code_Loc="(235,2),(235,27)">
<Variable
Id="112908"
Name="nres"
Access="Write"
Access_block="(573,8)"
Home_block="(573,8)"/>
</Data>
<Data
Data_owner="Jump"
Code_Loc="(236,2),(236,17)">
<Variable
Id="112909"
Name="result"
Access="Read"
Access_block="(573,8)"
Home_block="(573,8)"/>
</Data>
</Point_Block>
</CICB>
<CICB
Id="9"
Name="deccvint">
<Provide
Num_call_invokes="0"
Num_Variable_accesses="8">
<Call_invoke_IDs>
</Call_invoke_IDs>
<Variable_access_IDs>
112910
112911
112912
112913
112914
112915
112916
112917
</Variable_access_IDs>
</Provide>
<Require
Num_call_invokes="0"
Num_Variable_accesses="8">
<Call_invoke_IDs>
</Call_invoke_IDs>
<Variable_access_IDs>
112910
112911
112912
112913
112914
112915
112916
112917
</Variable_access_IDs>
</Require>
<Point_Block
Num_points="9"
Braced="Yes"
Code_Loc="(242,2),(258,17)">
<Data
Data_owner="VariableDeclaration"
Code_Loc="(243,2),(243,18)">
<Variable
Id="112910"
Name="result"
Access="Write"
Access_block="(573,9)"
Home_block="(573,9)"/>
</Data>
<Data
Data_owner="Expression"
Code_Loc="(245,2),(245,37)">
<Variable
Id="112911"
Name="np"
Access="Write"
Access_block="(573,9)"
Home_block="(573,9)"/>
</Data>
<Conditional
Code_Loc="(246,2),(247,11)">
</Conditional>
<Data
Data_owner="Expression"
Code_Loc="(249,2),(249,29)">
<Variable
Id="112912"
Name="nres"
Access="Write"
Access_block="(573,9)"
Home_block="(573,9)"/>
</Data>
<Conditional
Code_Loc="(250,2),(251,37)">
</Conditional>
<Data
Data_owner="Expression"
Code_Loc="(253,2),(253,44)">
<Variable
Id="112913"
Name="result"
Access="Write"
Access_block="(573,9)"
Home_block="(573,9)"/>
<Variable
Id="112914"
Name="in"
Access="Read"
Access_block="(573,9)"
Home_block="(573,9)"/>
<Variable
Id="112915"
Name="nres"
Access="Read"
Access_block="(573,9)"
Home_block="(573,9)"/>
</Data>
<Conditional
Code_Loc="(254,2),(255,47)">
</Conditional>
<Data
Data_owner="Expression"
Code_Loc="(257,2),(257,27)">
<Variable
Id="112916"
Name="nres"
Access="Write"
Access_block="(573,9)"
Home_block="(573,9)"/>
</Data>
<Data
Data_owner="Jump"
Code_Loc="(258,2),(258,17)">
<Variable
Id="112917"
Name="result"
Access="Read"
Access_block="(573,9)"
Home_block="(573,9)"/>
</Data>
</Point_Block>
</CICB>
<CICB
Id="10"
Name="deccvlong">
<Provide
Num_call_invokes="0"
Num_Variable_accesses="8">
<Call_invoke_IDs>
</Call_invoke_IDs>
<Variable_access_IDs>
112918
112919
112920
112921
112922
112923
112924
112925
</Variable_access_IDs>
</Provide>
<Require
Num_call_invokes="0"
Num_Variable_accesses="8">
<Call_invoke_IDs>
</Call_invoke_IDs>
<Variable_access_IDs>
112918
112919
112920
112921
112922
112923
112924
112925
</Variable_access_IDs>
</Require>
<Point_Block
Num_points="9"
Braced="Yes"
Code_Loc="(264,2),(280,17)">
<Data
Data_owner="VariableDeclaration"
Code_Loc="(265,2),(265,18)">
<Variable
Id="112918"
Name="result"
Access="Write"
Access_block="(573,10)"
Home_block="(573,10)"/>
</Data>
<Data
Data_owner="Expression"
Code_Loc="(267,2),(267,37)">
<Variable
Id="112919"
Name="np"
Access="Write"
Access_block="(573,10)"
Home_block="(573,10)"/>
</Data>
<Conditional
Code_Loc="(268,2),(269,11)">
</Conditional>
<Data
Data_owner="Expression"
Code_Loc="(271,2),(271,29)">
<Variable
Id="112920"
Name="nres"
Access="Write"
Access_block="(573,10)"
Home_block="(573,10)"/>
</Data>
<Conditional
Code_Loc="(272,2),(273,37)">
</Conditional>
<Data
Data_owner="Expression"
Code_Loc="(275,2),(275,46)">
<Variable
Id="112921"
Name="result"
Access="Write"
Access_block="(573,10)"
Home_block="(573,10)"/>
<Variable
Id="112922"
Name="lng"
Access="Read"
Access_block="(573,10)"
Home_block="(573,10)"/>
<Variable
Id="112923"
Name="nres"
Access="Read"
Access_block="(573,10)"
Home_block="(573,10)"/>
</Data>
<Conditional
Code_Loc="(276,2),(277,47)">
</Conditional>
<Data
Data_owner="Expression"
Code_Loc="(279,2),(279,27)">
<Variable
Id="112924"
Name="nres"
Access="Write"
Access_block="(573,10)"
Home_block="(573,10)"/>
</Data>
<Data
Data_owner="Jump"
Code_Loc="(280,2),(280,17)">
<Variable
Id="112925"
Name="result"
Access="Read"
Access_block="(573,10)"
Home_block="(573,10)"/>
</Data>
</Point_Block>
</CICB>
<CICB
Id="11"
Name="decdiv">
<Provide
Num_call_invokes="0"
Num_Variable_accesses="4">
<Call_invoke_IDs>
</Call_invoke_IDs>
<Variable_access_IDs>
112926
112927
112928
112929
</Variable_access_IDs>
</Provide>
<Require
Num_call_invokes="1"
Num_Variable_accesses="4">
<Call_invoke_IDs>
14448 
</Call_invoke_IDs>
<Variable_access_IDs>
112926
112927
112928
112929
</Variable_access_IDs>
</Require>
<Point_Block
Num_points="2"
Braced="Yes"
Code_Loc="(287,2),(306,10)">
<Data
Data_owner="Expression"
Code_Loc="(290,2),(290,50)">
<Variable
Id="112926"
Name="i"
Access="Write"
Access_block="(573,11)"
Home_block="(573,11)"/>
<Call
Id="14448"
Name="deccall3"
Collect="Emanated"
Access_block="(573,11)"
Home_block="(573,2)">
<Data
Data_owner="CallParamaters"
Code_Loc="(290,2),(290,50)">
<Variable
Id="112927"
Name="n1"
Access="Read"
Access_block="(573,11)"
Home_block="(573,11)"/>
<Variable
Id="112928"
Name="n2"
Access="Read"
Access_block="(573,11)"
Home_block="(573,11)"/>
<Variable
Id="112929"
Name="result"
Access="Read"
Access_block="(573,11)"
Home_block="(573,11)"/>
</Data>
</Call>
</Data>
<Conditional
Code_Loc="(292,2),(304,3)">
</Conditional>
</Point_Block>
</CICB>
<CICB
Id="12"
Name="decmul">
<Provide
Num_call_invokes="0"
Num_Variable_accesses="4">
<Call_invoke_IDs>
</Call_invoke_IDs>
<Variable_access_IDs>
112930
112931
112932
112933
</Variable_access_IDs>
</Provide>
<Require
Num_call_invokes="1"
Num_Variable_accesses="4">
<Call_invoke_IDs>
14449 
</Call_invoke_IDs>
<Variable_access_IDs>
112930
112931
112932
112933
</Variable_access_IDs>
</Require>
<Point_Block
Num_points="2"
Braced="Yes"
Code_Loc="(312,2),(328,10)">
<Data
Data_owner="Expression"
Code_Loc="(315,2),(315,50)">
<Variable
Id="112930"
Name="i"
Access="Write"
Access_block="(573,12)"
Home_block="(573,12)"/>
<Call
Id="14449"
Name="deccall3"
Collect="Emanated"
Access_block="(573,12)"
Home_block="(573,2)">
<Data
Data_owner="CallParamaters"
Code_Loc="(315,2),(315,50)">
<Variable
Id="112931"
Name="n1"
Access="Read"
Access_block="(573,12)"
Home_block="(573,12)"/>
<Variable
Id="112932"
Name="n2"
Access="Read"
Access_block="(573,12)"
Home_block="(573,12)"/>
<Variable
Id="112933"
Name="result"
Access="Read"
Access_block="(573,12)"
Home_block="(573,12)"/>
</Data>
</Call>
</Data>
<Conditional
Code_Loc="(317,2),(326,3)">
</Conditional>
</Point_Block>
</CICB>
<CICB
Id="13"
Name="decsub">
<Provide
Num_call_invokes="0"
Num_Variable_accesses="4">
<Call_invoke_IDs>
</Call_invoke_IDs>
<Variable_access_IDs>
112934
112935
112936
112937
</Variable_access_IDs>
</Provide>
<Require
Num_call_invokes="1"
Num_Variable_accesses="4">
<Call_invoke_IDs>
14450 
</Call_invoke_IDs>
<Variable_access_IDs>
112934
112935
112936
112937
</Variable_access_IDs>
</Require>
<Point_Block
Num_points="2"
Braced="Yes"
Code_Loc="(334,2),(350,10)">
<Data
Data_owner="Expression"
Code_Loc="(337,2),(337,50)">
<Variable
Id="112934"
Name="i"
Access="Write"
Access_block="(573,13)"
Home_block="(573,13)"/>
<Call
Id="14450"
Name="deccall3"
Collect="Emanated"
Access_block="(573,13)"
Home_block="(573,2)">
<Data
Data_owner="CallParamaters"
Code_Loc="(337,2),(337,50)">
<Variable
Id="112935"
Name="n1"
Access="Read"
Access_block="(573,13)"
Home_block="(573,13)"/>
<Variable
Id="112936"
Name="n2"
Access="Read"
Access_block="(573,13)"
Home_block="(573,13)"/>
<Variable
Id="112937"
Name="result"
Access="Read"
Access_block="(573,13)"
Home_block="(573,13)"/>
</Data>
</Call>
</Data>
<Conditional
Code_Loc="(339,2),(348,3)">
</Conditional>
</Point_Block>
</CICB>
<CICB
Id="14"
Name="dectoasc">
<Provide
Num_call_invokes="0"
Num_Variable_accesses="10">
<Call_invoke_IDs>
</Call_invoke_IDs>
<Variable_access_IDs>
112938
112939
112940
112941
112942
112943
112944
112945
112946
112947
</Variable_access_IDs>
</Provide>
<Require
Num_call_invokes="0"
Num_Variable_accesses="10">
<Call_invoke_IDs>
</Call_invoke_IDs>
<Variable_access_IDs>
112938
112939
112940
112941
112942
112943
112944
112945
112946
112947
</Variable_access_IDs>
</Require>
<Point_Block
Num_points="9"
Braced="Yes"
Code_Loc="(356,2),(401,2)">
<Data
Data_owner="Expression"
Code_Loc="(359,2),(359,36)">
<Variable
Id="112938"
Name="cp"
Access="Write"
Access_block="(573,14)"
Home_block="(573,14)"/>
</Data>
<Conditional
Code_Loc="(360,2),(361,11)">
</Conditional>
<Data
Data_owner="Expression"
Code_Loc="(363,2),(363,29)">
<Variable
Id="112939"
Name="nres"
Access="Write"
Access_block="(573,14)"
Home_block="(573,14)"/>
</Data>
<Conditional
Code_Loc="(364,2),(365,37)">
</Conditional>
<Conditional
Code_Loc="(367,2),(371,2)">
<Point_Block
Num_points="1"
Braced="Yes"
Code_Loc="(369,3),(370,37)">
<Data
Data_owner="Expression"
Code_Loc="(369,3),(369,28)">
<Variable
Id="112940"
Name="nres"
Access="Write"
Access_block="(573,14)"
Home_block="(573,14)"/>
</Data>
</Point_Block>
</Conditional>
<Selective
If_Blocks="Yes"
Code_Loc="(373,2),(376,50)">
</Selective>
<Data
Data_owner="Expression"
Code_Loc="(378,2),(378,27)">
<Variable
Id="112941"
Name="nres"
Access="Write"
Access_block="(573,14)"
Home_block="(573,14)"/>
</Data>
<Conditional
Code_Loc="(379,2),(380,12)">
</Conditional>
<Selective
If_Blocks="Yes"
Code_Loc="(386,2),(401,2)">
<Point_Block
Num_points="2"
Braced="Yes"
Code_Loc="(388,3),(394,12)">
<Conditional
Code_Loc="(388,3),(392,3)">
<Point_Block
Num_points="2"
Braced="Yes"
Code_Loc="(390,4),(391,16)">
<Data
Data_owner="Expression"
Code_Loc="(390,4),(390,15)">
<Variable
Id="112942"
Name="cp"
Access="Write"
Access_block="(573,14)"
Home_block="(573,14)"/>
</Data>
<Data
Data_owner="Expression"
Code_Loc="(391,4),(391,16)">
<Variable
Id="112943"
Name="cp"
Access="Write"
Access_block="(573,14)"
Home_block="(573,14)"/>
</Data>
</Point_Block>
</Conditional>
<Data
Data_owner="Expression"
Code_Loc="(393,3),(393,12)">
<Variable
Id="112944"
Name="str"
Access="Write"
Access_block="(573,14)"
Home_block="(573,14)"/>
</Data>
</Point_Block>
<Point_Block
Num_points="2"
Braced="Yes"
Code_Loc="(398,3),(400,11)">
<Data
Data_owner="Expression"
Code_Loc="(398,3),(398,18)">
<Variable
Id="112945"
Name="cp"
Access="Write"
Access_block="(573,14)"
Home_block="(573,14)"/>
<Variable
Id="112946"
Name="str"
Access="Read"
Access_block="(573,14)"
Home_block="(573,14)"/>
</Data>
<Data
Data_owner="Expression"
Code_Loc="(399,3),(399,12)">
<Variable
Id="112947"
Name="str"
Access="Write"
Access_block="(573,14)"
Home_block="(573,14)"/>
</Data>
</Point_Block>
</Selective>
</Point_Block>
</CICB>
<CICB
Id="15"
Name="dectodbl">
<Provide
Num_call_invokes="0"
Num_Variable_accesses="7">
<Call_invoke_IDs>
</Call_invoke_IDs>
<Variable_access_IDs>
112948
112949
112950
112951
112952
112953
112954
</Variable_access_IDs>
</Provide>
<Require
Num_call_invokes="0"
Num_Variable_accesses="7">
<Call_invoke_IDs>
</Call_invoke_IDs>
<Variable_access_IDs>
112948
112949
112950
112951
112952
112953
112954
</Variable_access_IDs>
</Require>
<Point_Block
Num_points="6"
Braced="Yes"
Code_Loc="(407,2),(422,10)">
<Data
Data_owner="VariableDeclaration"
Code_Loc="(408,2),(408,41)">
<Variable
Id="112948"
Name="nres"
Access="Write"
Access_block="(573,15)"
Home_block="(573,15)"/>
</Data>
<Conditional
Code_Loc="(410,2),(411,37)">
</Conditional>
<Conditional
Code_Loc="(413,2),(417,2)">
<Point_Block
Num_points="1"
Braced="Yes"
Code_Loc="(415,3),(416,37)">
<Data
Data_owner="Expression"
Code_Loc="(415,3),(415,28)">
<Variable
Id="112949"
Name="nres"
Access="Write"
Access_block="(573,15)"
Home_block="(573,15)"/>
</Data>
</Point_Block>
</Conditional>
<Data
Data_owner="Expression"
Code_Loc="(419,2),(419,42)">
<Variable
Id="112950"
Name="i"
Access="Write"
Access_block="(573,15)"
Home_block="(573,15)"/>
<Variable
Id="112951"
Name="nres"
Access="Read"
Access_block="(573,15)"
Home_block="(573,15)"/>
<Variable
Id="112952"
Name="dblp"
Access="Read"
Access_block="(573,15)"
Home_block="(573,15)"/>
</Data>
<Data
Data_owner="Expression"
Code_Loc="(420,2),(420,27)">
<Variable
Id="112953"
Name="nres"
Access="Write"
Access_block="(573,15)"
Home_block="(573,15)"/>
</Data>
<Data
Data_owner="Jump"
Code_Loc="(422,2),(422,10)">
<Variable
Id="112954"
Name="i"
Access="Read"
Access_block="(573,15)"
Home_block="(573,15)"/>
</Data>
</Point_Block>
</CICB>
<CICB
Id="16"
Name="dectoint">
<Provide
Num_call_invokes="0"
Num_Variable_accesses="7">
<Call_invoke_IDs>
</Call_invoke_IDs>
<Variable_access_IDs>
112955
112956
112957
112958
112959
112960
112961
</Variable_access_IDs>
</Provide>
<Require
Num_call_invokes="0"
Num_Variable_accesses="7">
<Call_invoke_IDs>
</Call_invoke_IDs>
<Variable_access_IDs>
112955
112956
112957
112958
112959
112960
112961
</Variable_access_IDs>
</Require>
<Point_Block
Num_points="7"
Braced="Yes"
Code_Loc="(428,2),(446,12)">
<Data
Data_owner="VariableDeclaration"
Code_Loc="(429,2),(429,41)">
<Variable
Id="112955"
Name="nres"
Access="Write"
Access_block="(573,16)"
Home_block="(573,16)"/>
</Data>
<Conditional
Code_Loc="(431,2),(432,37)">
</Conditional>
<Conditional
Code_Loc="(434,2),(438,2)">
<Point_Block
Num_points="1"
Braced="Yes"
Code_Loc="(436,3),(437,37)">
<Data
Data_owner="Expression"
Code_Loc="(436,3),(436,28)">
<Variable
Id="112956"
Name="nres"
Access="Write"
Access_block="(573,16)"
Home_block="(573,16)"/>
</Data>
</Point_Block>
</Conditional>
<Data
Data_owner="Expression"
Code_Loc="(440,2),(440,39)">
<Variable
Id="112957"
Name="ret"
Access="Write"
Access_block="(573,16)"
Home_block="(573,16)"/>
<Variable
Id="112958"
Name="nres"
Access="Read"
Access_block="(573,16)"
Home_block="(573,16)"/>
<Variable
Id="112959"
Name="ip"
Access="Read"
Access_block="(573,16)"
Home_block="(573,16)"/>
</Data>
<Data
Data_owner="Expression"
Code_Loc="(441,2),(441,27)">
<Variable
Id="112960"
Name="nres"
Access="Write"
Access_block="(573,16)"
Home_block="(573,16)"/>
</Data>
<Conditional
Code_Loc="(443,2),(444,35)">
</Conditional>
<Data
Data_owner="Jump"
Code_Loc="(446,2),(446,12)">
<Variable
Id="112961"
Name="ret"
Access="Read"
Access_block="(573,16)"
Home_block="(573,16)"/>
</Data>
</Point_Block>
</CICB>
<CICB
Id="17"
Name="dectolong">
<Provide
Num_call_invokes="0"
Num_Variable_accesses="7">
<Call_invoke_IDs>
</Call_invoke_IDs>
<Variable_access_IDs>
112962
112963
112964
112965
112966
112967
112968
</Variable_access_IDs>
</Provide>
<Require
Num_call_invokes="0"
Num_Variable_accesses="7">
<Call_invoke_IDs>
</Call_invoke_IDs>
<Variable_access_IDs>
112962
112963
112964
112965
112966
112967
112968
</Variable_access_IDs>
</Require>
<Point_Block
Num_points="7"
Braced="Yes"
Code_Loc="(452,2),(470,12)">
<Data
Data_owner="VariableDeclaration"
Code_Loc="(453,2),(453,41)">
<Variable
Id="112962"
Name="nres"
Access="Write"
Access_block="(573,17)"
Home_block="(573,17)"/>
</Data>
<Conditional
Code_Loc="(455,2),(456,37)">
</Conditional>
<Conditional
Code_Loc="(458,2),(462,2)">
<Point_Block
Num_points="1"
Braced="Yes"
Code_Loc="(460,3),(461,37)">
<Data
Data_owner="Expression"
Code_Loc="(460,3),(460,28)">
<Variable
Id="112963"
Name="nres"
Access="Write"
Access_block="(573,17)"
Home_block="(573,17)"/>
</Data>
</Point_Block>
</Conditional>
<Data
Data_owner="Expression"
Code_Loc="(464,2),(464,42)">
<Variable
Id="112964"
Name="ret"
Access="Write"
Access_block="(573,17)"
Home_block="(573,17)"/>
<Variable
Id="112965"
Name="nres"
Access="Read"
Access_block="(573,17)"
Home_block="(573,17)"/>
<Variable
Id="112966"
Name="lngp"
Access="Read"
Access_block="(573,17)"
Home_block="(573,17)"/>
</Data>
<Data
Data_owner="Expression"
Code_Loc="(465,2),(465,27)">
<Variable
Id="112967"
Name="nres"
Access="Write"
Access_block="(573,17)"
Home_block="(573,17)"/>
</Data>
<Conditional
Code_Loc="(467,2),(468,35)">
</Conditional>
<Data
Data_owner="Jump"
Code_Loc="(470,2),(470,12)">
<Variable
Id="112968"
Name="ret"
Access="Read"
Access_block="(573,17)"
Home_block="(573,17)"/>
</Data>
</Point_Block>
</CICB>
<CICB
Id="18"
Name="rdatestr">
<Provide
Num_call_invokes="0"
Num_Variable_accesses="5">
<Call_invoke_IDs>
</Call_invoke_IDs>
<Variable_access_IDs>
112969
112970
112971
112972
112973
</Variable_access_IDs>
</Provide>
<Require
Num_call_invokes="0"
Num_Variable_accesses="5">
<Call_invoke_IDs>
</Call_invoke_IDs>
<Variable_access_IDs>
112969
112970
112971
112972
112973
</Variable_access_IDs>
</Require>
<Point_Block
Num_points="4"
Braced="Yes"
Code_Loc="(477,2),(486,10)">
<Data
Data_owner="VariableDeclaration"
Code_Loc="(477,2),(477,38)">
<Variable
Id="112969"
Name="tmp"
Access="Write"
Access_block="(573,18)"
Home_block="(573,18)"/>
<Variable
Id="112970"
Name="d"
Access="Read"
Access_block="(573,18)"
Home_block="(573,18)"/>
</Data>
<Conditional
Code_Loc="(479,2),(480,36)">
</Conditional>
<Data
Data_owner="Expression"
Code_Loc="(483,2),(483,18)">
<Variable
Id="112971"
Name="str"
Access="Write"
Access_block="(573,18)"
Home_block="(573,18)"/>
<Variable
Id="112972"
Name="tmp"
Access="Read"
Access_block="(573,18)"
Home_block="(573,18)"/>
</Data>
<Data
Data_owner="Expression"
Code_Loc="(484,2),(484,11)">
<Variable
Id="112973"
Name="tmp"
Access="Write"
Access_block="(573,18)"
Home_block="(573,18)"/>
</Data>
</Point_Block>
</CICB>
<CICB
Id="19"
Name="rstrdate">
<Provide
Num_call_invokes="0"
Num_Variable_accesses="2">
<Call_invoke_IDs>
</Call_invoke_IDs>
<Variable_access_IDs>
112974
112975
</Variable_access_IDs>
</Provide>
<Require
Num_call_invokes="0"
Num_Variable_accesses="2">
<Call_invoke_IDs>
</Call_invoke_IDs>
<Variable_access_IDs>
112974
112975
</Variable_access_IDs>
</Require>
<Point_Block
Num_points="1"
Braced="Yes"
Code_Loc="(498,2),(498,41)">
<Data
Data_owner="Jump"
Code_Loc="(498,2),(498,41)">
<Variable
Id="112974"
Name="d"
Access="Read"
Access_block="(573,19)"
Home_block="(573,19)"/>
<Variable
Id="112975"
Name="str"
Access="Read"
Access_block="(573,19)"
Home_block="(573,19)"/>
</Data>
</Point_Block>
</CICB>
<CICB
Id="20"
Name="rtoday">
<Provide
Num_call_invokes="0"
Num_Variable_accesses="1">
<Call_invoke_IDs>
</Call_invoke_IDs>
<Variable_access_IDs>
112976
</Variable_access_IDs>
</Provide>
<Require
Num_call_invokes="0"
Num_Variable_accesses="1">
<Call_invoke_IDs>
</Call_invoke_IDs>
<Variable_access_IDs>
112976
</Variable_access_IDs>
</Require>
<Point_Block
Num_points="1"
Braced="Yes"
Code_Loc="(504,2),(505,8)">
<Data
Data_owner="Expression"
Code_Loc="(504,2),(504,22)">
<Variable
Id="112976"
Name="d"
Access="Write"
Access_block="(573,20)"
Home_block="(573,20)"/>
</Data>
</Point_Block>
</CICB>
<CICB
Id="21"
Name="rjulmdy">
<Provide
Num_call_invokes="0"
Num_Variable_accesses="8">
<Call_invoke_IDs>
</Call_invoke_IDs>
<Variable_access_IDs>
112977
112978
112979
112980
112981
112982
112983
112984
</Variable_access_IDs>
</Provide>
<Require
Num_call_invokes="0"
Num_Variable_accesses="8">
<Call_invoke_IDs>
</Call_invoke_IDs>
<Variable_access_IDs>
112977
112978
112979
112980
112981
112982
112983
112984
</Variable_access_IDs>
</Require>
<Point_Block
Num_points="4"
Braced="Yes"
Code_Loc="(511,2),(517,10)">
<Data
Data_owner="Expression"
Code_Loc="(513,2),(513,32)">
<Variable
Id="112977"
Name="d"
Access="Write"
Access_block="(573,21)"
Home_block="(573,21)"/>
<Variable
Id="112978"
Name="mdy_int"
Access="Read"
Access_block="(573,21)"
Home_block="(573,21)"/>
</Data>
<Data
Data_owner="Expression"
Code_Loc="(514,2),(514,29)">
<Variable
Id="112979"
Name="mdy"
Access="Write"
Access_block="(573,21)"
Home_block="(573,21)"/>
<Variable
Id="112980"
Name="mdy_int"
Access="Read"
Access_block="(573,21)"
Home_block="(573,21)"/>
</Data>
<Data
Data_owner="Expression"
Code_Loc="(515,2),(515,29)">
<Variable
Id="112981"
Name="mdy"
Access="Write"
Access_block="(573,21)"
Home_block="(573,21)"/>
<Variable
Id="112982"
Name="mdy_int"
Access="Read"
Access_block="(573,21)"
Home_block="(573,21)"/>
</Data>
<Data
Data_owner="Expression"
Code_Loc="(516,2),(516,29)">
<Variable
Id="112983"
Name="mdy"
Access="Write"
Access_block="(573,21)"
Home_block="(573,21)"/>
<Variable
Id="112984"
Name="mdy_int"
Access="Read"
Access_block="(573,21)"
Home_block="(573,21)"/>
</Data>
</Point_Block>
</CICB>
<CICB
Id="22"
Name="rfmtdate">
<Provide
Num_call_invokes="0"
Num_Variable_accesses="0">
<Call_invoke_IDs>
</Call_invoke_IDs>
<Variable_access_IDs>
</Variable_access_IDs>
</Provide>
<Require
Num_call_invokes="0"
Num_Variable_accesses="0">
<Call_invoke_IDs>
</Call_invoke_IDs>
<Variable_access_IDs>
</Variable_access_IDs>
</Require>
<Point_Block
Num_points="2"
Braced="Yes"
Code_Loc="(549,2),(556,35)">
<Conditional
Code_Loc="(550,2),(551,11)">
</Conditional>
<Conditional
Code_Loc="(553,2),(554,37)">
</Conditional>
</Point_Block>
</CICB>
<CICB
Id="23"
Name="rmdyjul">
<Provide
Num_call_invokes="0"
Num_Variable_accesses="8">
<Call_invoke_IDs>
</Call_invoke_IDs>
<Variable_access_IDs>
112985
112986
112987
112988
112989
112990
112991
112992
</Variable_access_IDs>
</Provide>
<Require
Num_call_invokes="0"
Num_Variable_accesses="8">
<Call_invoke_IDs>
</Call_invoke_IDs>
<Variable_access_IDs>
112985
112986
112987
112988
112989
112990
112991
112992
</Variable_access_IDs>
</Require>
<Point_Block
Num_points="4"
Braced="Yes"
Code_Loc="(562,2),(568,10)">
<Data
Data_owner="Expression"
Code_Loc="(564,2),(564,21)">
<Variable
Id="112985"
Name="mdy_int"
Access="Write"
Access_block="(573,23)"
Home_block="(573,23)"/>
<Variable
Id="112986"
Name="mdy"
Access="Read"
Access_block="(573,23)"
Home_block="(573,23)"/>
</Data>
<Data
Data_owner="Expression"
Code_Loc="(565,2),(565,21)">
<Variable
Id="112987"
Name="mdy_int"
Access="Write"
Access_block="(573,23)"
Home_block="(573,23)"/>
<Variable
Id="112988"
Name="mdy"
Access="Read"
Access_block="(573,23)"
Home_block="(573,23)"/>
</Data>
<Data
Data_owner="Expression"
Code_Loc="(566,2),(566,21)">
<Variable
Id="112989"
Name="mdy_int"
Access="Write"
Access_block="(573,23)"
Home_block="(573,23)"/>
<Variable
Id="112990"
Name="mdy"
Access="Read"
Access_block="(573,23)"
Home_block="(573,23)"/>
</Data>
<Data
Data_owner="Expression"
Code_Loc="(567,2),(567,32)">
<Variable
Id="112991"
Name="mdy_int"
Access="Write"
Access_block="(573,23)"
Home_block="(573,23)"/>
<Variable
Id="112992"
Name="d"
Access="Read"
Access_block="(573,23)"
Home_block="(573,23)"/>
</Data>
</Point_Block>
</CICB>
<CICB
Id="24"
Name="rdayofweek">
<Provide
Num_call_invokes="0"
Num_Variable_accesses="1">
<Call_invoke_IDs>
</Call_invoke_IDs>
<Variable_access_IDs>
112993
</Variable_access_IDs>
</Provide>
<Require
Num_call_invokes="0"
Num_Variable_accesses="1">
<Call_invoke_IDs>
</Call_invoke_IDs>
<Variable_access_IDs>
112993
</Variable_access_IDs>
</Require>
<Point_Block
Num_points="1"
Braced="Yes"
Code_Loc="(574,2),(574,35)">
<Data
Data_owner="Jump"
Code_Loc="(574,2),(574,35)">
<Variable
Id="112993"
Name="d"
Access="Read"
Access_block="(573,24)"
Home_block="(573,24)"/>
</Data>
</Point_Block>
</CICB>
<CICB
Id="25"
Name="dtcurrent">
<Provide
Num_call_invokes="0"
Num_Variable_accesses="1">
<Call_invoke_IDs>
</Call_invoke_IDs>
<Variable_access_IDs>
112994
</Variable_access_IDs>
</Provide>
<Require
Num_call_invokes="0"
Num_Variable_accesses="1">
<Call_invoke_IDs>
</Call_invoke_IDs>
<Variable_access_IDs>
112994
</Variable_access_IDs>
</Require>
<Point_Block
Num_points="1"
Braced="Yes"
Code_Loc="(582,2),(582,30)">
<Data
Data_owner="Expression"
Code_Loc="(582,2),(582,30)">
<Variable
Id="112994"
Name="ts"
Access="Write"
Access_block="(573,25)"
Home_block="(573,25)"/>
</Data>
</Point_Block>
</CICB>
<CICB
Id="26"
Name="dtcvasc">
<Provide
Num_call_invokes="0"
Num_Variable_accesses="8">
<Call_invoke_IDs>
</Call_invoke_IDs>
<Variable_access_IDs>
112995
112996
112997
112998
112999
113000
113001
113002
</Variable_access_IDs>
</Provide>
<Require
Num_call_invokes="0"
Num_Variable_accesses="8">
<Call_invoke_IDs>
</Call_invoke_IDs>
<Variable_access_IDs>
112995
112996
112997
112998
112999
113000
113001
113002
</Variable_access_IDs>
</Require>
<Point_Block
Num_points="6"
Braced="Yes"
Code_Loc="(588,2),(608,10)">
<Data
Data_owner="VariableDeclaration"
Code_Loc="(590,2),(590,24)">
<Variable
Id="112995"
Name="endptr"
Access="Write"
Access_block="(573,26)"
Home_block="(573,26)"/>
<Variable
Id="112996"
Name="str"
Access="Read"
Access_block="(573,26)"
Home_block="(573,26)"/>
</Data>
<Data
Data_owner="Expression"
Code_Loc="(593,2),(593,49)">
<Variable
Id="112997"
Name="ts_tmp"
Access="Write"
Access_block="(573,26)"
Home_block="(573,26)"/>
<Variable
Id="112998"
Name="str"
Access="Read"
Access_block="(573,26)"
Home_block="(573,26)"/>
<Variable
Id="112999"
Name="endptr"
Access="Read"
Access_block="(573,26)"
Home_block="(573,26)"/>
</Data>
<Data
Data_owner="Expression"
Code_Loc="(594,2),(594,11)">
<Variable
Id="113000"
Name="i"
Access="Write"
Access_block="(573,26)"
Home_block="(573,26)"/>
</Data>
<Conditional
Code_Loc="(595,2),(597,11)">
</Conditional>
<Conditional
Code_Loc="(598,2),(602,2)">
<Point_Block
Num_points="0"
Braced="Yes"
Code_Loc="(601,3),(601,35)">
</Point_Block>
</Conditional>
<Data
Data_owner="Expression"
Code_Loc="(606,2),(606,14)">
<Variable
Id="113001"
Name="ts"
Access="Write"
Access_block="(573,26)"
Home_block="(573,26)"/>
<Variable
Id="113002"
Name="ts_tmp"
Access="Read"
Access_block="(573,26)"
Home_block="(573,26)"/>
</Data>
</Point_Block>
</CICB>
<CICB
Id="27"
Name="dtcvfmtasc">
<Provide
Num_call_invokes="0"
Num_Variable_accesses="3">
<Call_invoke_IDs>
</Call_invoke_IDs>
<Variable_access_IDs>
113003
113004
113005
</Variable_access_IDs>
</Provide>
<Require
Num_call_invokes="0"
Num_Variable_accesses="3">
<Call_invoke_IDs>
</Call_invoke_IDs>
<Variable_access_IDs>
113003
113004
113005
</Variable_access_IDs>
</Require>
<Point_Block
Num_points="1"
Braced="Yes"
Code_Loc="(614,2),(614,59)">
<Data
Data_owner="Jump"
Code_Loc="(614,2),(614,59)">
<Variable
Id="113003"
Name="inbuf"
Access="Read"
Access_block="(573,27)"
Home_block="(573,27)"/>
<Variable
Id="113004"
Name="fmtstr"
Access="Read"
Access_block="(573,27)"
Home_block="(573,27)"/>
<Variable
Id="113005"
Name="dtvalue"
Access="Read"
Access_block="(573,27)"
Home_block="(573,27)"/>
</Data>
</Point_Block>
</CICB>
<CICB
Id="28"
Name="dtsub">
<Provide
Num_call_invokes="0"
Num_Variable_accesses="3">
<Call_invoke_IDs>
</Call_invoke_IDs>
<Variable_access_IDs>
113006
113007
113008
</Variable_access_IDs>
</Provide>
<Require
Num_call_invokes="0"
Num_Variable_accesses="3">
<Call_invoke_IDs>
</Call_invoke_IDs>
<Variable_access_IDs>
113006
113007
113008
</Variable_access_IDs>
</Require>
<Point_Block
Num_points="1"
Braced="Yes"
Code_Loc="(620,2),(620,43)">
<Data
Data_owner="Jump"
Code_Loc="(620,2),(620,43)">
<Variable
Id="113006"
Name="ts1"
Access="Read"
Access_block="(573,28)"
Home_block="(573,28)"/>
<Variable
Id="113007"
Name="ts2"
Access="Read"
Access_block="(573,28)"
Home_block="(573,28)"/>
<Variable
Id="113008"
Name="iv"
Access="Read"
Access_block="(573,28)"
Home_block="(573,28)"/>
</Data>
</Point_Block>
</CICB>
<CICB
Id="29"
Name="dttoasc">
<Provide
Num_call_invokes="0"
Num_Variable_accesses="5">
<Call_invoke_IDs>
</Call_invoke_IDs>
<Variable_access_IDs>
113009
113010
113011
113012
113013
</Variable_access_IDs>
</Provide>
<Require
Num_call_invokes="0"
Num_Variable_accesses="5">
<Call_invoke_IDs>
</Call_invoke_IDs>
<Variable_access_IDs>
113009
113010
113011
113012
113013
</Variable_access_IDs>
</Require>
<Point_Block
Num_points="3"
Braced="Yes"
Code_Loc="(626,2),(630,10)">
<Data
Data_owner="VariableDeclaration"
Code_Loc="(626,2),(626,49)">
<Variable
Id="113009"
Name="asctime"
Access="Write"
Access_block="(573,29)"
Home_block="(573,29)"/>
<Variable
Id="113010"
Name="ts"
Access="Read"
Access_block="(573,29)"
Home_block="(573,29)"/>
</Data>
<Data
Data_owner="Expression"
Code_Loc="(628,2),(628,25)">
<Variable
Id="113011"
Name="output"
Access="Write"
Access_block="(573,29)"
Home_block="(573,29)"/>
<Variable
Id="113012"
Name="asctime"
Access="Read"
Access_block="(573,29)"
Home_block="(573,29)"/>
</Data>
<Data
Data_owner="Expression"
Code_Loc="(629,2),(629,15)">
<Variable
Id="113013"
Name="asctime"
Access="Write"
Access_block="(573,29)"
Home_block="(573,29)"/>
</Data>
</Point_Block>
</CICB>
<CICB
Id="30"
Name="dttofmtasc">
<Provide
Num_call_invokes="0"
Num_Variable_accesses="4">
<Call_invoke_IDs>
</Call_invoke_IDs>
<Variable_access_IDs>
113014
113015
113016
113017
</Variable_access_IDs>
</Provide>
<Require
Num_call_invokes="0"
Num_Variable_accesses="4">
<Call_invoke_IDs>
</Call_invoke_IDs>
<Variable_access_IDs>
113014
113015
113016
113017
</Variable_access_IDs>
</Require>
<Point_Block
Num_points="1"
Braced="Yes"
Code_Loc="(636,2),(636,62)">
<Data
Data_owner="Jump"
Code_Loc="(636,2),(636,62)">
<Variable
Id="113014"
Name="ts"
Access="Read"
Access_block="(573,30)"
Home_block="(573,30)"/>
<Variable
Id="113015"
Name="output"
Access="Read"
Access_block="(573,30)"
Home_block="(573,30)"/>
<Variable
Id="113016"
Name="str_len"
Access="Read"
Access_block="(573,30)"
Home_block="(573,30)"/>
<Variable
Id="113017"
Name="fmtstr"
Access="Read"
Access_block="(573,30)"
Home_block="(573,30)"/>
</Data>
</Point_Block>
</CICB>
<CICB
Id="31"
Name="intoasc">
<Provide
Num_call_invokes="0"
Num_Variable_accesses="2">
<Call_invoke_IDs>
</Call_invoke_IDs>
<Variable_access_IDs>
113018
113019
</Variable_access_IDs>
</Provide>
<Require
Num_call_invokes="0"
Num_Variable_accesses="2">
<Call_invoke_IDs>
</Call_invoke_IDs>
<Variable_access_IDs>
113018
113019
</Variable_access_IDs>
</Require>
<Point_Block
Num_points="2"
Braced="Yes"
Code_Loc="(642,2),(648,10)">
<Data
Data_owner="Expression"
Code_Loc="(643,2),(643,33)">
<Variable
Id="113018"
Name="str"
Access="Write"
Access_block="(573,31)"
Home_block="(573,31)"/>
<Variable
Id="113019"
Name="i"
Access="Read"
Access_block="(573,31)"
Home_block="(573,31)"/>
</Data>
<Conditional
Code_Loc="(645,2),(646,16)">
</Conditional>
</Point_Block>
</CICB>
<CICB
Id="32"
Name="initValue">
<Provide
Num_call_invokes="0"
Num_Variable_accesses="18">
<Call_invoke_IDs>
</Call_invoke_IDs>
<Variable_access_IDs>
113020
113021
113022
113023
113024
113025
113026
113027
113028
113029
113030
113031
113032
113033
113034
113035
113036
113037
</Variable_access_IDs>
</Provide>
<Require
Num_call_invokes="0"
Num_Variable_accesses="28">
<Call_invoke_IDs>
</Call_invoke_IDs>
<Variable_access_IDs>
112827
113020
113021
113022
112828
113023
112829
113024
113025
113026
113027
112830
113028
113029
112831
112832
113030
112833
112834
113031
113032
113033
113034
113035
113036
113037
112835
112836
</Variable_access_IDs>
</Require>
<Point_Block
Num_points="12"
Braced="Yes"
Code_Loc="(673,2),(714,10)">
<Data
Data_owner="Expression"
Code_Loc="(679,2),(679,53)">
<Variable
Id="112827"
Name="value"
Access="Write"
Access_block="(573,32)"
Home_block="(573,0)"/>
<Variable
Id="113020"
Name="lng_val"
Access="Read"
Access_block="(573,32)"
Home_block="(573,32)"/>
<Variable
Id="113021"
Name="lng_val"
Access="Read"
Access_block="(573,32)"
Home_block="(573,32)"/>
<Variable
Id="113022"
Name="lng_val"
Access="Read"
Access_block="(573,32)"
Home_block="(573,32)"/>
</Data>
<Data
Data_owner="Expression"
Code_Loc="(680,2),(680,39)">
<Variable
Id="112828"
Name="value"
Access="Write"
Access_block="(573,32)"
Home_block="(573,0)"/>
<Variable
Id="113023"
Name="lng_val"
Access="Read"
Access_block="(573,32)"
Home_block="(573,32)"/>
</Data>
<Data
Data_owner="Expression"
Code_Loc="(681,2),(681,53)">
<Variable
Id="112829"
Name="value"
Access="Write"
Access_block="(573,32)"
Home_block="(573,0)"/>
</Data>
<Data
Data_owner="Expression"
Code_Loc="(684,2),(684,7)">
<Variable
Id="113024"
Name="i"
Access="Write"
Access_block="(573,32)"
Home_block="(573,32)"/>
</Data>
<Data
Data_owner="Expression"
Code_Loc="(685,2),(685,7)">
<Variable
Id="113025"
Name="l"
Access="Write"
Access_block="(573,32)"
Home_block="(573,32)"/>
</Data>
<Cyclic
Id="5495"
Code_Loc="(686,2),(691,51)">
<Point_Block
Num_points="2"
Braced="Yes"
Code_Loc="(688,3),(689,10)">
<Data
Data_owner="Expression"
Code_Loc="(688,3),(688,6)">
<Variable
Id="113026"
Name="i"
Access="Write"
Access_block="(573,32)"
Home_block="(573,32)"/>
</Data>
<Data
Data_owner="Expression"
Code_Loc="(689,3),(689,10)">
<Variable
Id="113027"
Name="l"
Access="Write"
Access_block="(573,32)"
Home_block="(573,32)"/>
</Data>
</Point_Block>
</Cyclic>
<Selective
If_Blocks="Yes"
Code_Loc="(693,2),(699,23)">
<Point_Block
Num_points="2"
Braced="Yes"
Code_Loc="(695,3),(696,10)">
<Data
Data_owner="Expression"
Code_Loc="(695,3),(695,19)">
<Variable
Id="112830"
Name="value"
Access="Write"
Access_block="(573,32)"
Home_block="(573,0)"/>
<Variable
Id="113028"
Name="i"
Access="Read"
Access_block="(573,32)"
Home_block="(573,32)"/>
</Data>
<Data
Data_owner="Expression"
Code_Loc="(696,3),(696,10)">
<Variable
Id="113029"
Name="l"
Access="Write"
Access_block="(573,32)"
Home_block="(573,32)"/>
</Data>
</Point_Block>
</Selective>
<Data
Data_owner="Expression"
Code_Loc="(701,2),(701,32)">
<Variable
Id="112831"
Name="value"
Access="Write"
Access_block="(573,32)"
Home_block="(573,0)"/>
<Variable
Id="112832"
Name="value"
Access="Read"
Access_block="(573,32)"
Home_block="(573,0)"/>
</Data>
<Conditional
Code_Loc="(704,2),(705,12)">
</Conditional>
<Data
Data_owner="Expression"
Code_Loc="(706,2),(706,17)">
<Variable
Id="113030"
Name="dig"
Access="Write"
Access_block="(573,32)"
Home_block="(573,32)"/>
<Variable
Id="112833"
Name="value"
Access="Read"
Access_block="(573,32)"
Home_block="(573,0)"/>
</Data>
<Cyclic
Id="5496"
Code_Loc="(707,2),(712,2)">
<Point_Block
Num_points="3"
Braced="Yes"
Code_Loc="(709,3),(711,10)">
<Data
Data_owner="Expression"
Code_Loc="(709,3),(709,38)">
<Variable
Id="112834"
Name="value"
Access="Write"
Access_block="(573,32)"
Home_block="(573,0)"/>
<Variable
Id="113031"
Name="j"
Access="Read"
Access_block="(573,32)"
Home_block="(573,32)"/>
<Variable
Id="113032"
Name="dig"
Access="Read"
Access_block="(573,32)"
Home_block="(573,32)"/>
<Variable
Id="113033"
Name="l"
Access="Read"
Access_block="(573,32)"
Home_block="(573,32)"/>
</Data>
<Data
Data_owner="Expression"
Code_Loc="(710,3),(710,16)">
<Variable
Id="113034"
Name="dig"
Access="Write"
Access_block="(573,32)"
Home_block="(573,32)"/>
<Variable
Id="113035"
Name="dig"
Access="Read"
Access_block="(573,32)"
Home_block="(573,32)"/>
<Variable
Id="113036"
Name="l"
Access="Read"
Access_block="(573,32)"
Home_block="(573,32)"/>
</Data>
<Data
Data_owner="Expression"
Code_Loc="(711,3),(711,10)">
<Variable
Id="113037"
Name="l"
Access="Write"
Access_block="(573,32)"
Home_block="(573,32)"/>
</Data>
</Point_Block>
</Cyclic>
<Data
Data_owner="Expression"
Code_Loc="(713,2),(713,39)">
<Variable
Id="112835"
Name="value"
Access="Write"
Access_block="(573,32)"
Home_block="(573,0)"/>
<Variable
Id="112836"
Name="value"
Access="Read"
Access_block="(573,32)"
Home_block="(573,0)"/>
</Data>
</Point_Block>
</CICB>
<CICB
Id="33"
Name="getRightMostDot">
<Provide
Num_call_invokes="1"
Num_Variable_accesses="4">
<Call_invoke_IDs>
14452 
</Call_invoke_IDs>
<Variable_access_IDs>
113038
113039
113040
113041
</Variable_access_IDs>
</Provide>
<Require
Num_call_invokes="0"
Num_Variable_accesses="4">
<Call_invoke_IDs>
</Call_invoke_IDs>
<Variable_access_IDs>
113038
113039
113040
113041
</Variable_access_IDs>
</Require>
<Point_Block
Num_points="3"
Braced="Yes"
Code_Loc="(721,2),(732,11)">
<Data
Data_owner="VariableDeclaration"
Code_Loc="(721,2),(721,27)">
<Variable
Id="113038"
Name="len"
Access="Write"
Access_block="(573,33)"
Home_block="(573,33)"/>
<Variable
Id="113039"
Name="str"
Access="Read"
Access_block="(573,33)"
Home_block="(573,33)"/>
</Data>
<Data
Data_owner="Expression"
Code_Loc="(725,2),(725,7)">
<Variable
Id="113040"
Name="j"
Access="Write"
Access_block="(573,33)"
Home_block="(573,33)"/>
</Data>
<Cyclic
Id="5497"
Code_Loc="(726,2),(731,2)">
<Point_Block
Num_points="2"
Braced="Yes"
Code_Loc="(728,3),(730,6)">
<Conditional
Code_Loc="(728,3),(729,22)">
</Conditional>
<Data
Data_owner="Expression"
Code_Loc="(730,3),(730,6)">
<Variable
Id="113041"
Name="j"
Access="Write"
Access_block="(573,33)"
Home_block="(573,33)"/>
</Data>
</Point_Block>
</Cyclic>
</Point_Block>
</CICB>
<CICB
Id="34"
Name="rfmtlong">
<Provide
Num_call_invokes="0"
Num_Variable_accesses="43">
<Call_invoke_IDs>
</Call_invoke_IDs>
<Variable_access_IDs>
113042
113043
113044
113045
113046
113047
113048
113049
113050
113051
113052
113053
113054
113055
113056
113057
113058
113059
113060
113061
113062
113063
113064
113065
113066
113067
113068
113069
113070
113071
113072
113073
113074
113075
113076
113077
113078
113079
113080
113081
113082
113083
113084
</Variable_access_IDs>
</Provide>
<Require
Num_call_invokes="1"
Num_Variable_accesses="47">
<Call_invoke_IDs>
14452 
</Call_invoke_IDs>
<Variable_access_IDs>
113042
113043
113044
113045
113046
113047
113048
113049
113050
113051
113052
113053
112837
113054
113055
113056
113057
113058
113059
112838
113060
113061
112839
113062
113063
113064
113065
113066
113067
113068
113069
113070
113071
113072
113073
113074
113075
113076
113077
113078
113079
113080
113081
113082
113083
113084
112840
</Variable_access_IDs>
</Require>
<Point_Block
Num_points="21"
Braced="Yes"
Code_Loc="(739,2),(931,10)">
<Data
Data_owner="VariableDeclaration"
Code_Loc="(739,2),(739,31)">
<Variable
Id="113042"
Name="fmt_len"
Access="Write"
Access_block="(573,34)"
Home_block="(573,34)"/>
<Variable
Id="113043"
Name="fmt"
Access="Read"
Access_block="(573,34)"
Home_block="(573,34)"/>
</Data>
<Data
Data_owner="VariableDeclaration"
Code_Loc="(745,2),(751,20)">
<Variable
Id="113044"
Name="leftalign"
Access="Write"
Access_block="(573,34)"
Home_block="(573,34)"/>
</Data>
<Data
Data_owner="VariableDeclaration"
Code_Loc="(753,2),(753,20)">
<Variable
Id="113045"
Name="tmp"
Access="Write"
Access_block="(573,34)"
Home_block="(573,34)"/>
</Data>
<Data
Data_owner="VariableDeclaration"
Code_Loc="(754,2),(755,18)">
<Variable
Id="113046"
Name="lastfmt"
Access="Write"
Access_block="(573,34)"
Home_block="(573,34)"/>
</Data>
<Data
Data_owner="Expression"
Code_Loc="(757,2),(757,37)">
<Variable
Id="113047"
Name="temp"
Access="Write"
Access_block="(573,34)"
Home_block="(573,34)"/>
<Variable
Id="113048"
Name="fmt_len"
Access="Read"
Access_block="(573,34)"
Home_block="(573,34)"/>
</Data>
<Conditional
Code_Loc="(758,2),(762,2)">
<Point_Block
Num_points="0"
Braced="Yes"
Code_Loc="(760,3),(761,12)">
</Point_Block>
</Conditional>
<Conditional
Code_Loc="(765,2),(770,2)">
<Point_Block
Num_points="1"
Braced="Yes"
Code_Loc="(767,3),(769,12)">
<Data
Data_owner="Expression"
Code_Loc="(767,3),(767,13)">
<Variable
Id="113049"
Name="temp"
Access="Write"
Access_block="(573,34)"
Home_block="(573,34)"/>
</Data>
</Point_Block>
</Conditional>
<Conditional
Code_Loc="(773,2),(774,16)">
</Conditional>
<Conditional
Code_Loc="(777,2),(778,18)">
</Conditional>
<Data
Data_owner="Expression"
Code_Loc="(782,2),(782,31)">
<Variable
Id="113050"
Name="dotpos"
Access="Write"
Access_block="(573,34)"
Home_block="(573,34)"/>
<Call
Id="14452"
Name="getRightMostDot"
Collect="Emanated"
Access_block="(573,34)"
Home_block="(573,33)">
</Call>
</Data>
<Data
Data_owner="Expression"
Code_Loc="(785,2),(785,16)">
<Variable
Id="113051"
Name="temp"
Access="Write"
Access_block="(573,34)"
Home_block="(573,34)"/>
</Data>
<Data
Data_owner="Expression"
Code_Loc="(786,2),(786,7)">
<Variable
Id="113052"
Name="j"
Access="Write"
Access_block="(573,34)"
Home_block="(573,34)"/>
</Data>
<Data
Data_owner="Expression"
Code_Loc="(787,2),(787,22)">
<Variable
Id="113053"
Name="k"
Access="Write"
Access_block="(573,34)"
Home_block="(573,34)"/>
<Variable
Id="112837"
Name="value"
Access="Read"
Access_block="(573,34)"
Home_block="(573,0)"/>
</Data>
<Cyclic
Id="5498"
Code_Loc="(788,2),(913,2)">
<Point_Block
Num_points="8"
Braced="Yes"
Code_Loc="(791,3),(912,6)">
<Conditional
Code_Loc="(791,3),(808,3)">
<Point_Block
Num_points="2"
Braced="Yes"
Code_Loc="(793,4),(807,4)">
<Selective
If_Blocks="Yes"
Code_Loc="(794,4),(797,13)">
</Selective>
<Conditional
Code_Loc="(798,4),(807,4)">
<Point_Block
Num_points="1"
Braced="Yes"
Code_Loc="(801,5),(806,6)">
<Conditional
Code_Loc="(801,5),(806,6)">
</Conditional>
</Point_Block>
</Conditional>
</Point_Block>
</Conditional>
<Conditional
Code_Loc="(810,3),(823,3)">
<Point_Block
Num_points="2"
Braced="Yes"
Code_Loc="(812,4),(822,12)">
<Selective
If_Blocks="Yes"
Code_Loc="(812,4),(820,17)">
<Point_Block
Num_points="1"
Braced="Yes"
Code_Loc="(814,5),(817,18)">
<Selective
If_Blocks="Yes"
Code_Loc="(814,5),(817,18)">
</Selective>
</Point_Block>
</Selective>
<Data
Data_owner="Expression"
Code_Loc="(821,4),(821,21)">
<Variable
Id="113054"
Name="temp"
Access="Write"
Access_block="(573,34)"
Home_block="(573,34)"/>
<Variable
Id="113055"
Name="tmp"
Access="Read"
Access_block="(573,34)"
Home_block="(573,34)"/>
</Data>
</Point_Block>
</Conditional>
<Selective
If_Blocks="Yes"
Code_Loc="(825,3),(828,20)">
</Selective>
<Conditional
Code_Loc="(830,3),(831,12)">
</Conditional>
<Selective
If_Blocks="No"
Code_Loc="(833,3),(909,3)">
<Point_Block
Num_points="2"
Braced="Yes"
Code_Loc="(836,5),(838,10)">
<Data
Data_owner="Expression"
Code_Loc="(836,5),(836,17)">
<Variable
Id="113056"
Name="tmp"
Access="Write"
Access_block="(573,34)"
Home_block="(573,34)"/>
</Data>
<Data
Data_owner="Expression"
Code_Loc="(837,5),(837,8)">
<Variable
Id="113057"
Name="k"
Access="Write"
Access_block="(573,34)"
Home_block="(573,34)"/>
</Data>
</Point_Block>
<Point_Block
Num_points="1"
Braced="Yes"
Code_Loc="(840,5),(844,10)">
<Selective
If_Blocks="Yes"
Code_Loc="(840,5),(843,34)">
</Selective>
</Point_Block>
<Point_Block
Num_points="1"
Braced="Yes"
Code_Loc="(846,5),(850,10)">
<Selective
If_Blocks="Yes"
Code_Loc="(846,5),(849,34)">
</Selective>
</Point_Block>
<Point_Block
Num_points="1"
Braced="Yes"
Code_Loc="(852,5),(856,10)">
<Selective
If_Blocks="Yes"
Code_Loc="(852,5),(855,34)">
</Selective>
</Point_Block>
<Point_Block
Num_points="1"
Braced="Yes"
Code_Loc="(858,5),(867,10)">
<Selective
If_Blocks="Yes"
Code_Loc="(858,5),(866,34)">
<Point_Block
Num_points="1"
Braced="Yes"
Code_Loc="(860,6),(861,18)">
<Data
Data_owner="Expression"
Code_Loc="(860,6),(860,18)">
<Variable
Id="113058"
Name="tmp"
Access="Write"
Access_block="(573,34)"
Home_block="(573,34)"/>
</Data>
</Point_Block>
</Selective>
</Point_Block>
<Point_Block
Num_points="1"
Braced="Yes"
Code_Loc="(869,5),(878,10)">
<Selective
If_Blocks="Yes"
Code_Loc="(869,5),(877,34)">
<Point_Block
Num_points="1"
Braced="Yes"
Code_Loc="(871,6),(872,18)">
<Data
Data_owner="Expression"
Code_Loc="(871,6),(871,25)">
<Variable
Id="113059"
Name="tmp"
Access="Write"
Access_block="(573,34)"
Home_block="(573,34)"/>
<Variable
Id="112838"
Name="value"
Access="Read"
Access_block="(573,34)"
Home_block="(573,0)"/>
</Data>
</Point_Block>
</Selective>
</Point_Block>
<Point_Block
Num_points="1"
Braced="Yes"
Code_Loc="(880,5),(886,10)">
<Selective
If_Blocks="Yes"
Code_Loc="(880,5),(885,34)">
</Selective>
</Point_Block>
<Point_Block
Num_points="1"
Braced="Yes"
Code_Loc="(888,5),(892,10)">
<Selective
If_Blocks="Yes"
Code_Loc="(888,5),(891,18)">
</Selective>
</Point_Block>
<Point_Block
Num_points="1"
Braced="Yes"
Code_Loc="(894,5),(903,10)">
<Selective
If_Blocks="Yes"
Code_Loc="(894,5),(902,34)">
<Point_Block
Num_points="1"
Braced="Yes"
Code_Loc="(896,6),(897,20)">
<Data
Data_owner="Expression"
Code_Loc="(896,6),(896,18)">
<Variable
Id="113060"
Name="tmp"
Access="Write"
Access_block="(573,34)"
Home_block="(573,34)"/>
</Data>
</Point_Block>
</Selective>
</Point_Block>
<Point_Block
Num_points="1"
Braced="Yes"
Code_Loc="(905,5),(906,10)">
<Data
Data_owner="Expression"
Code_Loc="(905,5),(905,33)">
<Variable
Id="113061"
Name="tmp"
Access="Write"
Access_block="(573,34)"
Home_block="(573,34)"/>
<Variable
Id="112839"
Name="value"
Access="Read"
Access_block="(573,34)"
Home_block="(573,0)"/>
<Variable
Id="113062"
Name="k"
Access="Read"
Access_block="(573,34)"
Home_block="(573,34)"/>
</Data>
</Point_Block>
<Point_Block
Num_points="1"
Braced="Yes"
Code_Loc="(908,5),(908,20)">
<Data
Data_owner="Expression"
Code_Loc="(908,5),(908,20)">
<Variable
Id="113063"
Name="tmp"
Access="Write"
Access_block="(573,34)"
Home_block="(573,34)"/>
<Variable
Id="113064"
Name="fmt"
Access="Read"
Access_block="(573,34)"
Home_block="(573,34)"/>
<Variable
Id="113065"
Name="i"
Access="Read"
Access_block="(573,34)"
Home_block="(573,34)"/>
</Data>
</Point_Block>
</Selective>
<Data
Data_owner="Expression"
Code_Loc="(910,3),(910,20)">
<Variable
Id="113066"
Name="temp"
Access="Write"
Access_block="(573,34)"
Home_block="(573,34)"/>
<Variable
Id="113067"
Name="tmp"
Access="Read"
Access_block="(573,34)"
Home_block="(573,34)"/>
</Data>
<Data
Data_owner="Expression"
Code_Loc="(911,3),(911,19)">
<Variable
Id="113068"
Name="lastfmt"
Access="Write"
Access_block="(573,34)"
Home_block="(573,34)"/>
<Variable
Id="113069"
Name="fmt"
Access="Read"
Access_block="(573,34)"
Home_block="(573,34)"/>
<Variable
Id="113070"
Name="i"
Access="Read"
Access_block="(573,34)"
Home_block="(573,34)"/>
</Data>
<Data
Data_owner="Expression"
Code_Loc="(912,3),(912,6)">
<Variable
Id="113071"
Name="k"
Access="Write"
Access_block="(573,34)"
Home_block="(573,34)"/>
</Data>
</Point_Block>
</Cyclic>
<Data
Data_owner="Expression"
Code_Loc="(915,2),(915,22)">
<Variable
Id="113072"
Name="temp"
Access="Write"
Access_block="(573,34)"
Home_block="(573,34)"/>
<Variable
Id="113073"
Name="fmt_len"
Access="Read"
Access_block="(573,34)"
Home_block="(573,34)"/>
</Data>
<Data
Data_owner="Expression"
Code_Loc="(918,2),(918,25)">
<Variable
Id="113074"
Name="temp_len"
Access="Write"
Access_block="(573,34)"
Home_block="(573,34)"/>
<Variable
Id="113075"
Name="temp"
Access="Read"
Access_block="(573,34)"
Home_block="(573,34)"/>
</Data>
<Data
Data_owner="Expression"
Code_Loc="(919,2),(919,18)">
<Variable
Id="113076"
Name="outbuf"
Access="Write"
Access_block="(573,34)"
Home_block="(573,34)"/>
</Data>
<Cyclic
Id="5499"
Code_Loc="(920,2),(924,2)">
<Point_Block
Num_points="2"
Braced="Yes"
Code_Loc="(922,3),(923,22)">
<Data
Data_owner="Expression"
Code_Loc="(922,3),(922,19)">
<Variable
Id="113077"
Name="tmp"
Access="Write"
Access_block="(573,34)"
Home_block="(573,34)"/>
<Variable
Id="113078"
Name="temp"
Access="Read"
Access_block="(573,34)"
Home_block="(573,34)"/>
<Variable
Id="113079"
Name="i"
Access="Read"
Access_block="(573,34)"
Home_block="(573,34)"/>
</Data>
<Data
Data_owner="Expression"
Code_Loc="(923,3),(923,22)">
<Variable
Id="113080"
Name="outbuf"
Access="Write"
Access_block="(573,34)"
Home_block="(573,34)"/>
<Variable
Id="113081"
Name="tmp"
Access="Read"
Access_block="(573,34)"
Home_block="(573,34)"/>
</Data>
</Point_Block>
</Cyclic>
<Data
Data_owner="Expression"
Code_Loc="(925,2),(925,25)">
<Variable
Id="113082"
Name="outbuf"
Access="Write"
Access_block="(573,34)"
Home_block="(573,34)"/>
<Variable
Id="113083"
Name="temp_len"
Access="Read"
Access_block="(573,34)"
Home_block="(573,34)"/>
</Data>
<Data
Data_owner="Expression"
Code_Loc="(928,2),(928,12)">
<Variable
Id="113084"
Name="temp"
Access="Write"
Access_block="(573,34)"
Home_block="(573,34)"/>
</Data>
<Data
Data_owner="Expression"
Code_Loc="(929,2),(929,24)">
<Variable
Id="112840"
Name="value"
Access="Write"
Access_block="(573,34)"
Home_block="(573,0)"/>
</Data>
</Point_Block>
</CICB>
<CICB
Id="35"
Name="rupshift">
<Provide
Num_call_invokes="0"
Num_Variable_accesses="0">
<Call_invoke_IDs>
</Call_invoke_IDs>
<Variable_access_IDs>
</Variable_access_IDs>
</Provide>
<Require
Num_call_invokes="0"
Num_Variable_accesses="0">
<Call_invoke_IDs>
</Call_invoke_IDs>
<Variable_access_IDs>
</Variable_access_IDs>
</Require>
<Point_Block
Num_points="1"
Braced="Yes"
Code_Loc="(937,2),(940,8)">
<Cyclic
Id="5500"
Code_Loc="(937,2),(939,40)">
</Cyclic>
</Point_Block>
</CICB>
<CICB
Id="36"
Name="byleng">
<Provide
Num_call_invokes="1"
Num_Variable_accesses="1">
<Call_invoke_IDs>
14453 
</Call_invoke_IDs>
<Variable_access_IDs>
113085
</Variable_access_IDs>
</Provide>
<Require
Num_call_invokes="0"
Num_Variable_accesses="1">
<Call_invoke_IDs>
</Call_invoke_IDs>
<Variable_access_IDs>
113085
</Variable_access_IDs>
</Require>
<Point_Block
Num_points="2"
Braced="Yes"
Code_Loc="(946,2),(947,18)">
<Cyclic
Id="5501"
Code_Loc="(946,2),(946,49)">
</Cyclic>
<Data
Data_owner="Jump"
Code_Loc="(947,2),(947,18)">
<Variable
Id="113085"
Name="len"
Access="Read"
Access_block="(573,36)"
Home_block="(573,36)"/>
</Data>
</Point_Block>
</CICB>
<CICB
Id="37"
Name="ldchar">
<Provide
Num_call_invokes="0"
Num_Variable_accesses="7">
<Call_invoke_IDs>
</Call_invoke_IDs>
<Variable_access_IDs>
113086
113087
113088
113089
113090
113091
113092
</Variable_access_IDs>
</Provide>
<Require
Num_call_invokes="1"
Num_Variable_accesses="7">
<Call_invoke_IDs>
14453 
</Call_invoke_IDs>
<Variable_access_IDs>
113086
113087
113088
113089
113090
113091
113092
</Variable_access_IDs>
</Require>
<Point_Block
Num_points="3"
Braced="Yes"
Code_Loc="(953,2),(956,19)">
<Data
Data_owner="VariableDeclaration"
Code_Loc="(953,2),(953,31)">
<Variable
Id="113086"
Name="dlen"
Access="Write"
Access_block="(573,37)"
Home_block="(573,37)"/>
<Call
Id="14453"
Name="byleng"
Collect="Emanated"
Access_block="(573,37)"
Home_block="(573,36)">
<Data
Data_owner="CallParamaters"
Code_Loc="(953,2),(953,31)">
<Variable
Id="113087"
Name="src"
Access="Read"
Access_block="(573,37)"
Home_block="(573,37)"/>
</Data>
</Call>
</Data>
<Data
Data_owner="Expression"
Code_Loc="(955,2),(955,26)">
<Variable
Id="113088"
Name="dest"
Access="Write"
Access_block="(573,37)"
Home_block="(573,37)"/>
<Variable
Id="113089"
Name="src"
Access="Read"
Access_block="(573,37)"
Home_block="(573,37)"/>
<Variable
Id="113090"
Name="dlen"
Access="Read"
Access_block="(573,37)"
Home_block="(573,37)"/>
</Data>
<Data
Data_owner="Expression"
Code_Loc="(956,2),(956,19)">
<Variable
Id="113091"
Name="dest"
Access="Write"
Access_block="(573,37)"
Home_block="(573,37)"/>
<Variable
Id="113092"
Name="dlen"
Access="Read"
Access_block="(573,37)"
Home_block="(573,37)"/>
</Data>
</Point_Block>
</CICB>
<CICB
Id="38"
Name="rgetmsg">
<Provide
Num_call_invokes="0"
Num_Variable_accesses="0">
<Call_invoke_IDs>
</Call_invoke_IDs>
<Variable_access_IDs>
</Variable_access_IDs>
</Provide>
<Require
Num_call_invokes="0"
Num_Variable_accesses="0">
<Call_invoke_IDs>
</Call_invoke_IDs>
<Variable_access_IDs>
</Variable_access_IDs>
</Require>
<Point_Block
Num_points="0"
Braced="Yes"
Code_Loc="(962,2),(962,10)">
</Point_Block>
</CICB>
<CICB
Id="39"
Name="rtypalign">
<Provide
Num_call_invokes="0"
Num_Variable_accesses="0">
<Call_invoke_IDs>
</Call_invoke_IDs>
<Variable_access_IDs>
</Variable_access_IDs>
</Provide>
<Require
Num_call_invokes="0"
Num_Variable_accesses="0">
<Call_invoke_IDs>
</Call_invoke_IDs>
<Variable_access_IDs>
</Variable_access_IDs>
</Require>
<Point_Block
Num_points="0"
Braced="Yes"
Code_Loc="(968,2),(968,10)">
</Point_Block>
</CICB>
<CICB
Id="40"
Name="rtypmsize">
<Provide
Num_call_invokes="0"
Num_Variable_accesses="0">
<Call_invoke_IDs>
</Call_invoke_IDs>
<Variable_access_IDs>
</Variable_access_IDs>
</Provide>
<Require
Num_call_invokes="0"
Num_Variable_accesses="0">
<Call_invoke_IDs>
</Call_invoke_IDs>
<Variable_access_IDs>
</Variable_access_IDs>
</Require>
<Point_Block
Num_points="0"
Braced="Yes"
Code_Loc="(974,2),(974,10)">
</Point_Block>
</CICB>
<CICB
Id="41"
Name="rtypwidth">
<Provide
Num_call_invokes="0"
Num_Variable_accesses="0">
<Call_invoke_IDs>
</Call_invoke_IDs>
<Variable_access_IDs>
</Variable_access_IDs>
</Provide>
<Require
Num_call_invokes="0"
Num_Variable_accesses="0">
<Call_invoke_IDs>
</Call_invoke_IDs>
<Variable_access_IDs>
</Variable_access_IDs>
</Require>
<Point_Block
Num_points="0"
Braced="Yes"
Code_Loc="(980,2),(980,10)">
</Point_Block>
</CICB>
<CICB
Id="42"
Name="ECPG_informix_set_var">
<Provide
Num_call_invokes="0"
Num_Variable_accesses="8">
<Call_invoke_IDs>
</Call_invoke_IDs>
<Variable_access_IDs>
113093
113094
113095
113096
113097
113098
113099
113100
</Variable_access_IDs>
</Provide>
<Require
Num_call_invokes="0"
Num_Variable_accesses="10">
<Call_invoke_IDs>
</Call_invoke_IDs>
<Variable_access_IDs>
113093
113094
113095
113096
113097
113098
113099
113100
112841
112842
</Variable_access_IDs>
</Require>
<Point_Block
Num_points="2"
Braced="Yes"
Code_Loc="(993,2),(1024,2)">
<Cyclic
Id="5502"
Code_Loc="(995,2),(1003,2)">
<Point_Block
Num_points="1"
Braced="Yes"
Code_Loc="(997,3),(1002,3)">
<Conditional
Code_Loc="(997,3),(1002,3)">
<Point_Block
Num_points="0"
Braced="Yes"
Code_Loc="(1000,4),(1001,10)">
</Point_Block>
</Conditional>
</Point_Block>
</Cyclic>
<Selective
If_Blocks="Yes"
Code_Loc="(1007,2),(1024,2)">
<Point_Block
Num_points="5"
Braced="Yes"
Code_Loc="(1009,3),(1016,22)">
<Data
Data_owner="VariableDeclaration"
Code_Loc="(1009,3),(1009,42)">
<Variable
Id="113093"
Name="sqlca"
Access="Write"
Access_block="(573,42)"
Home_block="(573,42)"/>
</Data>
<Data
Data_owner="Expression"
Code_Loc="(1011,3),(1011,38)">
<Variable
Id="113094"
Name="sqlca"
Access="Write"
Access_block="(573,42)"
Home_block="(573,42)"/>
</Data>
<Data
Data_owner="Expression"
Code_Loc="(1012,3),(1012,53)">
<Variable
Id="113095"
Name="sqlca"
Access="Write"
Access_block="(573,42)"
Home_block="(573,42)"/>
</Data>
<Data
Data_owner="Expression"
Code_Loc="(1013,3),(1013,105)">
<Variable
Id="113096"
Name="sqlca"
Access="Write"
Access_block="(573,42)"
Home_block="(573,42)"/>
<Variable
Id="113097"
Name="sqlca"
Access="Read"
Access_block="(573,42)"
Home_block="(573,42)"/>
<Variable
Id="113098"
Name="lineno"
Access="Read"
Access_block="(573,42)"
Home_block="(573,42)"/>
</Data>
<Data
Data_owner="Expression"
Code_Loc="(1014,3),(1014,60)">
<Variable
Id="113099"
Name="sqlca"
Access="Write"
Access_block="(573,42)"
Home_block="(573,42)"/>
<Variable
Id="113100"
Name="sqlca"
Access="Read"
Access_block="(573,42)"
Home_block="(573,42)"/>
</Data>
</Point_Block>
<Point_Block
Num_points="2"
Braced="Yes"
Code_Loc="(1020,3),(1023,15)">
<Data
Data_owner="Expression"
Code_Loc="(1022,3),(1022,21)">
<Variable
Id="112841"
Name="ivlist"
Access="Write"
Access_block="(573,42)"
Home_block="(573,0)"/>
</Data>
<Data
Data_owner="Expression"
Code_Loc="(1023,3),(1023,15)">
<Variable
Id="112842"
Name="ivlist"
Access="Write"
Access_block="(573,42)"
Home_block="(573,0)"/>
</Data>
</Point_Block>
</Selective>
</Point_Block>
</CICB>
<CICB
Id="43"
Name="ECPG_informix_get_var">
<Provide
Num_call_invokes="0"
Num_Variable_accesses="0">
<Call_invoke_IDs>
</Call_invoke_IDs>
<Variable_access_IDs>
</Variable_access_IDs>
</Provide>
<Require
Num_call_invokes="0"
Num_Variable_accesses="0">
<Call_invoke_IDs>
</Call_invoke_IDs>
<Variable_access_IDs>
</Variable_access_IDs>
</Require>
<Point_Block
Num_points="1"
Braced="Yes"
Code_Loc="(1030,2),(1033,36)">
<Cyclic
Id="5503"
Code_Loc="(1032,2),(1032,75)">
</Cyclic>
</Point_Block>
</CICB>
</Component>
