<?xml version = "1.0"?>
<!DOCTYPE Component [
<!ELEMENT Component (CICB*)>
<!ATTLIST Component
Id CDATA #REQUIRED
Name CDATA #REQUIRED
Num_CICBs CDATA #REQUIRED>
<!ELEMENT CICB (Provide|Require|Block_Point|EMPTY)>
<!ATTLIST CICB
Id CDATA #REQUIRED
Name CDATA #REQUIRED>
<!ELEMENT Provide (Call_invoke_IDs|Variable_access_IDs|EMPTY)>
<!ATTLIST Provide
Num_call_invokes CDATA #REQUIRED
Num_Variable_accesses CDATA #REQUIRED>
<!ELEMENT Require (Call_invoke_IDs|Variable_access_IDs|EMPTY)>
<!ATTLIST Provide
Num_call_invokes CDATA #REQUIRED
Num_Variable_accesses CDATA #REQUIRED>
<!ELEMENT Call_invoke_IDs EMPTY>
<!ELEMENT Variable_access_IDs EMPTY>
<!ELEMENT Point_Block (Selective|Conditional|Cyclic|Data)*>
<!ATTLIST Provide
Num_points CDATA #REQUIRED
Braced CDATA #REQUIRED
Code_Loc CDATA #REQUIRED>
<!ELEMENT Selective (Point_Block*|EMPTY)>
<!ATTLIST Selective
If_Blocks CDATA #REQUIRED
Code_Loc CDATA #REQUIRED>
<!ELEMENT Conditional (Point_Block|EMPTY)>
<!ATTLIST Conditional
Code_Loc CDATA #REQUIRED>
<!ELEMENT Cyclic (Point_Block|EMPTY)>
<!ATTLIST Cyclic
Id CDATA #REQUIRED
Code_Loc CDATA #REQUIRED>
<!ELEMENT Data (Call|Variable|EMPTY)*>
<!ATTLIST Data
Data_owner CDATA #REQUIRED
Code_Loc CDATA #REQUIRED>
<!ELEMENT Call (Data|EMPTY)>
<!ATTLIST Call
Id CDATA #REQUIRED
Name CDATA #REQUIRED
Collect CDATA #REQUIRED
Access_block CDATA #REQUIRED
Home_block CDATA #REQUIRED>
<!ELEMENT Variable EMPTY>
<!ATTLIST Variable
Id CDATA #REQUIRED
Name CDATA #REQUIRED
Access CDATA #REQUIRED
Access_block CDATA #REQUIRED
Home_block CDATA #REQUIRED>
]>
<Component
Id="268"
Name="backend.port.sysv_shmem.c"
Num_CICBs="8">
<CICB
Id="0"
Name="Master">
<Provide
Num_call_invokes="0"
Num_Variable_accesses="7">
<Call_invoke_IDs>
</Call_invoke_IDs>
<Variable_access_IDs>
50692
50693
50694
50695
50696
50697
50698
</Variable_access_IDs>
</Provide>
<Require
Num_call_invokes="0"
Num_Variable_accesses="2">
<Call_invoke_IDs>
</Call_invoke_IDs>
<Variable_access_IDs>
50692
50693
</Variable_access_IDs>
</Require>
<Point_Block
Num_points="2"
Braced="Yes"
Code_Loc="(38,1),(534,1)">
<Data
Data_owner="VariableDeclaration"
Code_Loc="(50,1),(50,33)">
<Variable
Id="50692"
Name="UsedShmemSegID"
Access="Write"
Access_block="(268,0)"
Home_block="(268,0)"/>
</Data>
<Data
Data_owner="VariableDeclaration"
Code_Loc="(51,1),(51,33)">
<Variable
Id="50693"
Name="UsedShmemSegAddr"
Access="Write"
Access_block="(268,0)"
Home_block="(268,0)"/>
</Data>
</Point_Block>
</CICB>
<CICB
Id="1"
Name="InternalIpcMemoryCreate">
<Provide
Num_call_invokes="2"
Num_Variable_accesses="15">
<Call_invoke_IDs>
8922 
8923 
</Call_invoke_IDs>
<Variable_access_IDs>
50699
50700
50701
50702
50703
50704
50705
50706
50707
50708
50711
50714
50717
50718
50719
</Variable_access_IDs>
</Provide>
<Require
Num_call_invokes="4"
Num_Variable_accesses="21">
<Call_invoke_IDs>
8918 
8919 
8920 
8921 
</Call_invoke_IDs>
<Variable_access_IDs>
50699
50700
50701
50702
50703
50704
50705
50706
50707
50708
50709
50710
50711
50712
50713
50714
50715
50716
50717
50718
50719
</Variable_access_IDs>
</Require>
<Point_Block
Num_points="7"
Braced="Yes"
Code_Loc="(75,2),(197,19)">
<Data
Data_owner="Expression"
Code_Loc="(78,2),(78,68)">
<Variable
Id="50699"
Name="shmid"
Access="Write"
Access_block="(268,1)"
Home_block="(268,1)"/>
<Variable
Id="50700"
Name="memKey"
Access="Read"
Access_block="(268,1)"
Home_block="(268,1)"/>
<Variable
Id="50701"
Name="size"
Access="Read"
Access_block="(268,1)"
Home_block="(268,1)"/>
</Data>
<Conditional
Code_Loc="(80,2),(179,2)">
<Point_Block
Num_points="3"
Braced="Yes"
Code_Loc="(88,3),(178,58)">
<Conditional
Code_Loc="(88,3),(93,15)">
</Conditional>
<Conditional
Code_Loc="(104,3),(135,3)">
<Point_Block
Num_points="4"
Braced="Yes"
Code_Loc="(106,4),(134,22)">
<Data
Data_owner="VariableDeclaration"
Code_Loc="(106,4),(106,27)">
<Variable
Id="50702"
Name="save_errno"
Access="Write"
Access_block="(268,1)"
Home_block="(268,1)"/>
</Data>
<Data
Data_owner="Expression"
Code_Loc="(108,4),(108,67)">
<Variable
Id="50703"
Name="shmid"
Access="Write"
Access_block="(268,1)"
Home_block="(268,1)"/>
<Variable
Id="50704"
Name="memKey"
Access="Read"
Access_block="(268,1)"
Home_block="(268,1)"/>
</Data>
<Selective
If_Blocks="Yes"
Code_Loc="(110,4),(132,4)">
<Point_Block
Num_points="1"
Braced="Yes"
Code_Loc="(113,5),(118,17)">
<Conditional
Code_Loc="(113,5),(118,17)">
</Conditional>
</Point_Block>
<Point_Block
Num_points="1"
Braced="Yes"
Code_Loc="(129,5),(131,30)">
<Conditional
Code_Loc="(129,5),(131,30)">
</Conditional>
</Point_Block>
</Selective>
<Data
Data_owner="Expression"
Code_Loc="(134,4),(134,22)">
<Variable
Id="50705"
Name="save_errno"
Access="Write"
Access_block="(268,1)"
Home_block="(268,1)"/>
</Data>
</Point_Block>
</Conditional>
<Data
Data_owner="Expression"
Code_Loc="(140,3),(178,58)">
<Variable
Id="50706"
Name="memKey"
Access="Write"
Access_block="(268,1)"
Home_block="(268,1)"/>
<Variable
Id="50707"
Name="size"
Access="Read"
Access_block="(268,1)"
Home_block="(268,1)"/>
<Variable
Id="50708"
Name="size"
Access="Read"
Access_block="(268,1)"
Home_block="(268,1)"/>
<Variable
Id="50709"
Name="NBuffers"
Access="Read"
Access_block="(268,1)"
Home_block="(927,0)"/>
<Variable
Id="50710"
Name="MaxBackends"
Access="Read"
Access_block="(268,1)"
Home_block="(927,0)"/>
<Variable
Id="50711"
Name="size"
Access="Read"
Access_block="(268,1)"
Home_block="(268,1)"/>
<Variable
Id="50712"
Name="NBuffers"
Access="Read"
Access_block="(268,1)"
Home_block="(927,0)"/>
<Variable
Id="50713"
Name="MaxBackends"
Access="Read"
Access_block="(268,1)"
Home_block="(927,0)"/>
<Variable
Id="50714"
Name="size"
Access="Read"
Access_block="(268,1)"
Home_block="(268,1)"/>
<Variable
Id="50715"
Name="NBuffers"
Access="Read"
Access_block="(268,1)"
Home_block="(927,0)"/>
<Variable
Id="50716"
Name="MaxBackends"
Access="Read"
Access_block="(268,1)"
Home_block="(927,0)"/>
</Data>
</Point_Block>
</Conditional>
<Data
Data_owner="Expression"
Code_Loc="(182,2),(182,54)">
<Call
Id="8918"
Name="on_shmem_exit"
Collect="Bridged"
Access_block="(268,1)"
Home_block="(343,5)">
<Data
Data_owner="CallParamaters"
Code_Loc="(182,2),(182,54)">
<Call
Id="8919"
Name="IpcMemoryDelete"
Collect="Absorbed"
Access_block="(268,1)"
Home_block="(268,3)">
</Call>
</Data>
</Call>
</Data>
<Data
Data_owner="Expression"
Code_Loc="(185,2),(185,49)">
<Variable
Id="50717"
Name="memAddress"
Access="Write"
Access_block="(268,1)"
Home_block="(268,1)"/>
<Variable
Id="50718"
Name="shmid"
Access="Read"
Access_block="(268,1)"
Home_block="(268,1)"/>
</Data>
<Conditional
Code_Loc="(187,2),(188,48)">
</Conditional>
<Data
Data_owner="Expression"
Code_Loc="(191,2),(191,61)">
<Call
Id="8920"
Name="on_shmem_exit"
Collect="Bridged"
Access_block="(268,1)"
Home_block="(343,5)">
<Data
Data_owner="CallParamaters"
Code_Loc="(191,2),(191,61)">
<Call
Id="8921"
Name="IpcMemoryDetach"
Collect="Absorbed"
Access_block="(268,1)"
Home_block="(268,2)">
</Call>
</Data>
</Call>
</Data>
<Data
Data_owner="Jump"
Code_Loc="(197,2),(197,19)">
<Variable
Id="50719"
Name="memAddress"
Access="Read"
Access_block="(268,1)"
Home_block="(268,1)"/>
</Data>
</Point_Block>
</CICB>
<CICB
Id="2"
Name="IpcMemoryDetach">
<Provide
Num_call_invokes="1"
Num_Variable_accesses="0">
<Call_invoke_IDs>
8921 
</Call_invoke_IDs>
<Variable_access_IDs>
</Variable_access_IDs>
</Provide>
<Require
Num_call_invokes="0"
Num_Variable_accesses="0">
<Call_invoke_IDs>
</Call_invoke_IDs>
<Variable_access_IDs>
</Variable_access_IDs>
</Require>
<Point_Block
Num_points="1"
Braced="Yes"
Code_Loc="(208,2),(209,62)">
<Conditional
Code_Loc="(208,2),(209,62)">
</Conditional>
</Point_Block>
</CICB>
<CICB
Id="3"
Name="IpcMemoryDelete">
<Provide
Num_call_invokes="1"
Num_Variable_accesses="0">
<Call_invoke_IDs>
8919 
</Call_invoke_IDs>
<Variable_access_IDs>
</Variable_access_IDs>
</Provide>
<Require
Num_call_invokes="0"
Num_Variable_accesses="0">
<Call_invoke_IDs>
</Call_invoke_IDs>
<Variable_access_IDs>
</Variable_access_IDs>
</Require>
<Point_Block
Num_points="1"
Braced="Yes"
Code_Loc="(219,2),(221,36)">
<Conditional
Code_Loc="(219,2),(221,36)">
</Conditional>
</Point_Block>
</CICB>
<CICB
Id="4"
Name="PGSharedMemoryIsInUse">
<Provide
Num_call_invokes="0"
Num_Variable_accesses="6">
<Call_invoke_IDs>
</Call_invoke_IDs>
<Variable_access_IDs>
50720
50721
50722
50723
50724
50725
</Variable_access_IDs>
</Provide>
<Require
Num_call_invokes="0"
Num_Variable_accesses="6">
<Call_invoke_IDs>
</Call_invoke_IDs>
<Variable_access_IDs>
50720
50721
50722
50723
50724
50725
</Variable_access_IDs>
</Require>
<Point_Block
Num_points="8"
Braced="Yes"
Code_Loc="(238,2),(317,13)">
<Data
Data_owner="VariableDeclaration"
Code_Loc="(238,2),(238,39)">
<Variable
Id="50720"
Name="shmId"
Access="Write"
Access_block="(268,4)"
Home_block="(268,4)"/>
<Variable
Id="50721"
Name="id2"
Access="Read"
Access_block="(268,4)"
Home_block="(268,4)"/>
</Data>
<Conditional
Code_Loc="(247,2),(283,2)">
<Point_Block
Num_points="3"
Braced="Yes"
Code_Loc="(254,3),(282,14)">
<Conditional
Code_Loc="(254,3),(255,16)">
</Conditional>
<Conditional
Code_Loc="(262,3),(263,16)">
</Conditional>
<Conditional
Code_Loc="(273,3),(274,16)">
</Conditional>
</Point_Block>
</Conditional>
<Conditional
Code_Loc="(286,2),(287,15)">
</Conditional>
<Conditional
Code_Loc="(294,2),(295,14)">
</Conditional>
<Data
Data_owner="Expression"
Code_Loc="(297,2),(297,60)">
<Variable
Id="50722"
Name="hdr"
Access="Write"
Access_block="(268,4)"
Home_block="(268,4)"/>
<Variable
Id="50723"
Name="shmId"
Access="Read"
Access_block="(268,4)"
Home_block="(268,4)"/>
</Data>
<Conditional
Code_Loc="(299,2),(300,14)">
</Conditional>
<Conditional
Code_Loc="(302,2),(312,2)">
<Point_Block
Num_points="1"
Braced="Yes"
Code_Loc="(310,3),(311,15)">
<Data
Data_owner="Expression"
Code_Loc="(310,3),(310,22)">
<Variable
Id="50724"
Name="hdr"
Access="Write"
Access_block="(268,4)"
Home_block="(268,4)"/>
</Data>
</Point_Block>
</Conditional>
<Data
Data_owner="Expression"
Code_Loc="(315,2),(315,21)">
<Variable
Id="50725"
Name="hdr"
Access="Write"
Access_block="(268,4)"
Home_block="(268,4)"/>
</Data>
</Point_Block>
</CICB>
<CICB
Id="5"
Name="PGSharedMemoryCreate">
<Provide
Num_call_invokes="0"
Num_Variable_accesses="25">
<Call_invoke_IDs>
</Call_invoke_IDs>
<Variable_access_IDs>
50726
50727
50728
50729
50730
50731
50732
50733
50734
50735
50736
50737
50738
50739
50740
50741
50742
50743
50744
50745
50746
50747
50748
50749
50750
</Variable_access_IDs>
</Provide>
<Require
Num_call_invokes="2"
Num_Variable_accesses="28">
<Call_invoke_IDs>
8922 
8923 
</Call_invoke_IDs>
<Variable_access_IDs>
50726
50694
50727
50728
50729
50730
50731
50732
50733
50734
50735
50736
50737
50738
50739
50740
50741
50742
50743
50744
50745
50746
50747
50695
50748
50696
50749
50750
</Variable_access_IDs>
</Require>
<Point_Block
Num_points="15"
Braced="Yes"
Code_Loc="(342,2),(438,12)">
<Data
Data_owner="Expression"
Code_Loc="(349,2),(349,48)">
<Variable
Id="50726"
Name="size"
Access="Write"
Access_block="(268,5)"
Home_block="(268,5)"/>
</Data>
<Data
Data_owner="Expression"
Code_Loc="(352,2),(352,25)">
<Variable
Id="50694"
Name="UsedShmemSegAddr"
Access="Write"
Access_block="(268,5)"
Home_block="(268,0)"/>
</Data>
<Data
Data_owner="Expression"
Code_Loc="(355,2),(355,30)">
<Variable
Id="50727"
Name="NextShmemSegID"
Access="Write"
Access_block="(268,5)"
Home_block="(268,5)"/>
<Variable
Id="50728"
Name="port"
Access="Read"
Access_block="(268,5)"
Home_block="(268,5)"/>
</Data>
<Cyclic
Id="3043"
Code_Loc="(357,2),(408,2)">
<Point_Block
Num_points="10"
Braced="Yes"
Code_Loc="(360,3),(401,9)">
<Data
Data_owner="Expression"
Code_Loc="(360,3),(360,61)">
<Variable
Id="50729"
Name="memAddress"
Access="Write"
Access_block="(268,5)"
Home_block="(268,5)"/>
<Call
Id="8922"
Name="InternalIpcMemoryCreate"
Collect="Emanated"
Access_block="(268,5)"
Home_block="(268,1)">
<Data
Data_owner="CallParamaters"
Code_Loc="(360,3),(360,61)">
<Variable
Id="50730"
Name="NextShmemSegID"
Access="Read"
Access_block="(268,5)"
Home_block="(268,5)"/>
</Data>
</Call>
</Data>
<Conditional
Code_Loc="(361,3),(362,9)">
</Conditional>
<Conditional
Code_Loc="(366,3),(367,12)">
</Conditional>
<Conditional
Code_Loc="(369,3),(370,12)">
</Conditional>
<Data
Data_owner="Expression"
Code_Loc="(376,3),(376,37)">
<Variable
Id="50731"
Name="hdr"
Access="Write"
Access_block="(268,5)"
Home_block="(268,5)"/>
<Variable
Id="50732"
Name="memAddress"
Access="Read"
Access_block="(268,5)"
Home_block="(268,5)"/>
</Data>
<Conditional
Code_Loc="(377,3),(384,3)">
<Point_Block
Num_points="1"
Braced="Yes"
Code_Loc="(379,4),(383,4)">
<Conditional
Code_Loc="(379,4),(383,4)">
<Point_Block
Num_points="1"
Braced="Yes"
Code_Loc="(381,5),(382,13)">
<Data
Data_owner="Expression"
Code_Loc="(381,5),(381,22)">
<Variable
Id="50733"
Name="memAddress"
Access="Write"
Access_block="(268,5)"
Home_block="(268,5)"/>
</Data>
</Point_Block>
</Conditional>
</Point_Block>
</Conditional>
<Data
Data_owner="Expression"
Code_Loc="(392,3),(392,20)">
<Variable
Id="50734"
Name="memAddress"
Access="Write"
Access_block="(268,5)"
Home_block="(268,5)"/>
</Data>
<Conditional
Code_Loc="(393,3),(394,12)">
</Conditional>
<Data
Data_owner="Expression"
Code_Loc="(399,3),(399,61)">
<Variable
Id="50735"
Name="memAddress"
Access="Write"
Access_block="(268,5)"
Home_block="(268,5)"/>
<Call
Id="8923"
Name="InternalIpcMemoryCreate"
Collect="Emanated"
Access_block="(268,5)"
Home_block="(268,1)">
<Data
Data_owner="CallParamaters"
Code_Loc="(399,3),(399,61)">
<Variable
Id="50736"
Name="NextShmemSegID"
Access="Read"
Access_block="(268,5)"
Home_block="(268,5)"/>
</Data>
</Call>
</Data>
<Conditional
Code_Loc="(400,3),(401,9)">
</Conditional>
</Point_Block>
</Cyclic>
<Data
Data_owner="Expression"
Code_Loc="(415,2),(415,36)">
<Variable
Id="50737"
Name="hdr"
Access="Write"
Access_block="(268,5)"
Home_block="(268,5)"/>
<Variable
Id="50738"
Name="memAddress"
Access="Read"
Access_block="(268,5)"
Home_block="(268,5)"/>
</Data>
<Data
Data_owner="Expression"
Code_Loc="(416,2),(416,28)">
<Variable
Id="50739"
Name="hdr"
Access="Write"
Access_block="(268,5)"
Home_block="(268,5)"/>
</Data>
<Data
Data_owner="Expression"
Code_Loc="(417,2),(417,27)">
<Variable
Id="50740"
Name="hdr"
Access="Write"
Access_block="(268,5)"
Home_block="(268,5)"/>
</Data>
<Conditional
Code_Loc="(420,2),(424,17)">
</Conditional>
<Data
Data_owner="Expression"
Code_Loc="(425,2),(425,30)">
<Variable
Id="50741"
Name="hdr"
Access="Write"
Access_block="(268,5)"
Home_block="(268,5)"/>
<Variable
Id="50742"
Name="statbuf"
Access="Read"
Access_block="(268,5)"
Home_block="(268,5)"/>
</Data>
<Data
Data_owner="Expression"
Code_Loc="(426,2),(426,29)">
<Variable
Id="50743"
Name="hdr"
Access="Write"
Access_block="(268,5)"
Home_block="(268,5)"/>
<Variable
Id="50744"
Name="statbuf"
Access="Read"
Access_block="(268,5)"
Home_block="(268,5)"/>
</Data>
<Data
Data_owner="Expression"
Code_Loc="(431,2),(431,23)">
<Variable
Id="50745"
Name="hdr"
Access="Write"
Access_block="(268,5)"
Home_block="(268,5)"/>
<Variable
Id="50746"
Name="size"
Access="Read"
Access_block="(268,5)"
Home_block="(268,5)"/>
</Data>
<Data
Data_owner="Expression"
Code_Loc="(432,2),(432,51)">
<Variable
Id="50747"
Name="hdr"
Access="Write"
Access_block="(268,5)"
Home_block="(268,5)"/>
</Data>
<Data
Data_owner="Expression"
Code_Loc="(435,2),(435,31)">
<Variable
Id="50695"
Name="UsedShmemSegAddr"
Access="Write"
Access_block="(268,5)"
Home_block="(268,0)"/>
<Variable
Id="50748"
Name="memAddress"
Access="Read"
Access_block="(268,5)"
Home_block="(268,5)"/>
</Data>
<Data
Data_owner="Expression"
Code_Loc="(436,2),(436,49)">
<Variable
Id="50696"
Name="UsedShmemSegID"
Access="Write"
Access_block="(268,5)"
Home_block="(268,0)"/>
<Variable
Id="50749"
Name="NextShmemSegID"
Access="Read"
Access_block="(268,5)"
Home_block="(268,5)"/>
</Data>
<Data
Data_owner="Jump"
Code_Loc="(438,2),(438,12)">
<Variable
Id="50750"
Name="hdr"
Access="Read"
Access_block="(268,5)"
Home_block="(268,5)"/>
</Data>
</Point_Block>
</CICB>
<CICB
Id="6"
Name="PGSharedMemoryDetach">
<Provide
Num_call_invokes="0"
Num_Variable_accesses="0">
<Call_invoke_IDs>
</Call_invoke_IDs>
<Variable_access_IDs>
</Variable_access_IDs>
</Provide>
<Require
Num_call_invokes="0"
Num_Variable_accesses="1">
<Call_invoke_IDs>
</Call_invoke_IDs>
<Variable_access_IDs>
50697
</Variable_access_IDs>
</Require>
<Point_Block
Num_points="1"
Braced="Yes"
Code_Loc="(495,2),(505,2)">
<Conditional
Code_Loc="(495,2),(505,2)">
<Point_Block
Num_points="2"
Braced="Yes"
Code_Loc="(497,3),(504,26)">
<Conditional
Code_Loc="(497,3),(503,55)">
</Conditional>
<Data
Data_owner="Expression"
Code_Loc="(504,3),(504,26)">
<Variable
Id="50697"
Name="UsedShmemSegAddr"
Access="Write"
Access_block="(268,6)"
Home_block="(268,0)"/>
</Data>
</Point_Block>
</Conditional>
</Point_Block>
</CICB>
<CICB
Id="7"
Name="PGSharedMemoryAttach">
<Provide
Num_call_invokes="0"
Num_Variable_accesses="4">
<Call_invoke_IDs>
</Call_invoke_IDs>
<Variable_access_IDs>
50751
50752
50753
50754
</Variable_access_IDs>
</Provide>
<Require
Num_call_invokes="0"
Num_Variable_accesses="5">
<Call_invoke_IDs>
</Call_invoke_IDs>
<Variable_access_IDs>
50751
50752
50698
50753
50754
</Variable_access_IDs>
</Require>
<Point_Block
Num_points="5"
Braced="Yes"
Code_Loc="(517,2),(533,12)">
<Conditional
Code_Loc="(519,2),(520,14)">
</Conditional>
<Data
Data_owner="Expression"
Code_Loc="(522,2),(522,73)">
<Variable
Id="50751"
Name="hdr"
Access="Write"
Access_block="(268,7)"
Home_block="(268,7)"/>
<Variable
Id="50752"
Name="shmid"
Access="Read"
Access_block="(268,7)"
Home_block="(268,7)"/>
<Variable
Id="50698"
Name="UsedShmemSegAddr"
Access="Read"
Access_block="(268,7)"
Home_block="(268,0)"/>
</Data>
<Conditional
Code_Loc="(524,2),(525,14)">
</Conditional>
<Conditional
Code_Loc="(527,2),(531,2)">
<Point_Block
Num_points="1"
Braced="Yes"
Code_Loc="(529,3),(530,14)">
<Data
Data_owner="Expression"
Code_Loc="(529,3),(529,22)">
<Variable
Id="50753"
Name="hdr"
Access="Write"
Access_block="(268,7)"
Home_block="(268,7)"/>
</Data>
</Point_Block>
</Conditional>
<Data
Data_owner="Jump"
Code_Loc="(533,2),(533,12)">
<Variable
Id="50754"
Name="hdr"
Access="Read"
Access_block="(268,7)"
Home_block="(268,7)"/>
</Data>
</Point_Block>
</CICB>
</Component>
